{
  "gold_price_id": 1,
  "from": "2017-08-06",
  "to": "2017-11-02",
  "fetched_at": "2026-07-08T05:20:43Z",
  "count": 269,
  "data": [
    {
      "Id": 0,
      "TypeName": "Vàng SJC 1L, 10L, 1KG",
      "BranchName": "Hồ Chí Minh",
      "Buy": "36,120",
      "BuyValue": 36120000.0,
      "Sell": "36,320",
      "SellValue": 36320000.0,
      "BuyDiffer": null,
      "BuyDifferValue": 0,
      "SellDiffer": null,
      "SellDifferValue": 0,
      "GroupDate": "/Date(1501952400000)/"
    },
    {
      "Id": 0,
      "TypeName": "Vàng SJC 1L, 10L, 1KG",
      "BranchName": "Hồ Chí Minh",
      "Buy": "36,300",
      "BuyValue": 36300000.0,
      "Sell": "36,500",
      "SellValue": 36500000.0,
      "BuyDiffer": null,
      "BuyDifferValue": 0,
      "SellDiffer": null,
      "SellDifferValue": 0,
      "GroupDate": "/Date(1502389774000)/"
    },
    {
      "Id": 0,
      "TypeName": "Vàng SJC 1L, 10L, 1KG",
      "BranchName": "Hồ Chí Minh",
      "Buy": "36,340",
      "BuyValue": 36340000.0,
      "Sell": "36,540",
      "SellValue": 36540000.0,
      "BuyDiffer": null,
      "BuyDifferValue": 0,
      "SellDiffer": null,
      "SellDifferValue": 0,
      "GroupDate": "/Date(1502397786000)/"
    },
    {
      "Id": 0,
      "TypeName": "Vàng SJC 1L, 10L, 1KG",
      "BranchName": "Hồ Chí Minh",
      "Buy": "36,320",
      "BuyValue": 36320000.0,
      "Sell": "36,520",
      "SellValue": 36520000.0,
      "BuyDiffer": null,
      "BuyDifferValue": 0,
      "SellDiffer": null,
      "SellDifferValue": 0,
      "GroupDate": "/Date(1502408538000)/"
    },
    {
      "Id": 0,
      "TypeName": "Vàng SJC 1L, 10L, 1KG",
      "BranchName": "Hồ Chí Minh",
      "Buy": "36,330",
      "BuyValue": 36330000.0,
      "Sell": "36,530",
      "SellValue": 36530000.0,
      "BuyDiffer": null,
      "BuyDifferValue": 0,
      "SellDiffer": null,
      "SellDifferValue": 0,
      "GroupDate": "/Date(1502411415000)/"
    },
    {
      "Id": 0,
      "TypeName": "Vàng SJC 1L, 10L, 1KG",
      "BranchName": "Hồ Chí Minh",
      "Buy": "36,350",
      "BuyValue": 36350000.0,
      "Sell": "36,550",
      "SellValue": 36550000.0,
      "BuyDiffer": null,
      "BuyDifferValue": 0,
      "SellDiffer": null,
      "SellDifferValue": 0,
      "GroupDate": "/Date(1502476249000)/"
    },
    {
      "Id": 0,
      "TypeName": "Vàng SJC 1L, 10L, 1KG",
      "BranchName": "Hồ Chí Minh",
      "Buy": "36,320",
      "BuyValue": 36320000.0,
      "Sell": "36,520",
      "SellValue": 36520000.0,
      "BuyDiffer": null,
      "BuyDifferValue": 0,
      "SellDiffer": null,
      "SellDifferValue": 0,
      "GroupDate": "/Date(1502648059000)/"
    },
    {
      "Id": 0,
      "TypeName": "Vàng SJC 1L, 10L, 1KG",
      "BranchName": "Hồ Chí Minh",
      "Buy": "36,330",
      "BuyValue": 36330000.0,
      "Sell": "36,530",
      "SellValue": 36530000.0,
      "BuyDiffer": null,
      "BuyDifferValue": 0,
      "SellDiffer": null,
      "SellDifferValue": 0,
      "GroupDate": "/Date(1502652777000)/"
    },
    {
      "Id": 0,
      "TypeName": "Vàng SJC 1L, 10L, 1KG",
      "BranchName": "Hồ Chí Minh",
      "Buy": "36,310",
      "BuyValue": 36310000.0,
      "Sell": "36,510",
      "SellValue": 36510000.0,
      "BuyDiffer": null,
      "BuyDifferValue": 0,
      "SellDiffer": null,
      "SellDifferValue": 0,
      "GroupDate": "/Date(1502654566000)/"
    },
    {
      "Id": 0,
      "TypeName": "Vàng SJC 1L, 10L, 1KG",
      "BranchName": "Hồ Chí Minh",
      "Buy": "36,320",
      "BuyValue": 36320000.0,
      "Sell": "36,520",
      "SellValue": 36520000.0,
      "BuyDiffer": null,
      "BuyDifferValue": 0,
      "SellDiffer": null,
      "SellDifferValue": 0,
      "GroupDate": "/Date(1502655578000)/"
    },
    {
      "Id": 0,
      "TypeName": "Vàng SJC 1L, 10L, 1KG",
      "BranchName": "Hồ Chí Minh",
      "Buy": "36,300",
      "BuyValue": 36300000.0,
      "Sell": "36,500",
      "SellValue": 36500000.0,
      "BuyDiffer": null,
      "BuyDifferValue": 0,
      "SellDiffer": null,
      "SellDifferValue": 0,
      "GroupDate": "/Date(1502659377000)/"
    },
    {
      "Id": 0,
      "TypeName": "Vàng SJC 1L, 10L, 1KG",
      "BranchName": "Hồ Chí Minh",
      "Buy": "36,290",
      "BuyValue": 36290000.0,
      "Sell": "36,490",
      "SellValue": 36490000.0,
      "BuyDiffer": null,
      "BuyDifferValue": 0,
      "SellDiffer": null,
      "SellDifferValue": 0,
      "GroupDate": "/Date(1502671859000)/"
    },
    {
      "Id": 0,
      "TypeName": "Vàng SJC 1L, 10L, 1KG",
      "BranchName": "Hồ Chí Minh",
      "Buy": "36,280",
      "BuyValue": 36280000.0,
      "Sell": "36,480",
      "SellValue": 36480000.0,
      "BuyDiffer": null,
      "BuyDifferValue": 0,
      "SellDiffer": null,
      "SellDifferValue": 0,
      "GroupDate": "/Date(1502672260000)/"
    },
    {
      "Id": 0,
      "TypeName": "Vàng SJC 1L, 10L, 1KG",
      "BranchName": "Hồ Chí Minh",
      "Buy": "36,240",
      "BuyValue": 36240000.0,
      "Sell": "36,440",
      "SellValue": 36440000.0,
      "BuyDiffer": null,
      "BuyDifferValue": 0,
      "SellDiffer": null,
      "SellDifferValue": 0,
      "GroupDate": "/Date(1502734286000)/"
    },
    {
      "Id": 0,
      "TypeName": "Vàng SJC 1L, 10L, 1KG",
      "BranchName": "Hồ Chí Minh",
      "Buy": "36,220",
      "BuyValue": 36220000.0,
      "Sell": "36,420",
      "SellValue": 36420000.0,
      "BuyDiffer": null,
      "BuyDifferValue": 0,
      "SellDiffer": null,
      "SellDifferValue": 0,
      "GroupDate": "/Date(1502734706000)/"
    },
    {
      "Id": 0,
      "TypeName": "Vàng SJC 1L, 10L, 1KG",
      "BranchName": "Hồ Chí Minh",
      "Buy": "36,200",
      "BuyValue": 36200000.0,
      "Sell": "36,400",
      "SellValue": 36400000.0,
      "BuyDiffer": null,
      "BuyDifferValue": 0,
      "SellDiffer": null,
      "SellDifferValue": 0,
      "GroupDate": "/Date(1502739027000)/"
    },
    {
      "Id": 0,
      "TypeName": "Vàng SJC 1L, 10L, 1KG",
      "BranchName": "Hồ Chí Minh",
      "Buy": "36,190",
      "BuyValue": 36190000.0,
      "Sell": "36,390",
      "SellValue": 36390000.0,
      "BuyDiffer": null,
      "BuyDifferValue": 0,
      "SellDiffer": null,
      "SellDifferValue": 0,
      "GroupDate": "/Date(1502758354000)/"
    },
    {
      "Id": 0,
      "TypeName": "Vàng SJC 1L, 10L, 1KG",
      "BranchName": "Hồ Chí Minh",
      "Buy": "36,150",
      "BuyValue": 36150000.0,
      "Sell": "36,350",
      "SellValue": 36350000.0,
      "BuyDiffer": null,
      "BuyDifferValue": 0,
      "SellDiffer": null,
      "SellDifferValue": 0,
      "GroupDate": "/Date(1502821057000)/"
    },
    {
      "Id": 0,
      "TypeName": "Vàng SJC 1L, 10L, 1KG",
      "BranchName": "Hồ Chí Minh",
      "Buy": "36,130",
      "BuyValue": 36130000.0,
      "Sell": "36,330",
      "SellValue": 36330000.0,
      "BuyDiffer": null,
      "BuyDifferValue": 0,
      "SellDiffer": null,
      "SellDifferValue": 0,
      "GroupDate": "/Date(1502841105000)/"
    },
    {
      "Id": 0,
      "TypeName": "Vàng SJC 1L, 10L, 1KG",
      "BranchName": "Hồ Chí Minh",
      "Buy": "36,260",
      "BuyValue": 36260000.0,
      "Sell": "36,460",
      "SellValue": 36460000.0,
      "BuyDiffer": null,
      "BuyDifferValue": 0,
      "SellDiffer": null,
      "SellDifferValue": 0,
      "GroupDate": "/Date(1502907971000)/"
    },
    {
      "Id": 0,
      "TypeName": "Vàng SJC 1L, 10L, 1KG",
      "BranchName": "Hồ Chí Minh",
      "Buy": "36,250",
      "BuyValue": 36250000.0,
      "Sell": "36,450",
      "SellValue": 36450000.0,
      "BuyDiffer": null,
      "BuyDifferValue": 0,
      "SellDiffer": null,
      "SellDifferValue": 0,
      "GroupDate": "/Date(1502912521000)/"
    },
    {
      "Id": 0,
      "TypeName": "Vàng SJC 1L, 10L, 1KG",
      "BranchName": "Hồ Chí Minh",
      "Buy": "36,240",
      "BuyValue": 36240000.0,
      "Sell": "36,440",
      "SellValue": 36440000.0,
      "BuyDiffer": null,
      "BuyDifferValue": 0,
      "SellDiffer": null,
      "SellDifferValue": 0,
      "GroupDate": "/Date(1502994102000)/"
    },
    {
      "Id": 0,
      "TypeName": "Vàng SJC 1L, 10L, 1KG",
      "BranchName": "Hồ Chí Minh",
      "Buy": "36,270",
      "BuyValue": 36270000.0,
      "Sell": "36,470",
      "SellValue": 36470000.0,
      "BuyDiffer": null,
      "BuyDifferValue": 0,
      "SellDiffer": null,
      "SellDifferValue": 0,
      "GroupDate": "/Date(1503014756000)/"
    },
    {
      "Id": 0,
      "TypeName": "Vàng SJC 1L, 10L, 1KG",
      "BranchName": "Hồ Chí Minh",
      "Buy": "36,300",
      "BuyValue": 36300000.0,
      "Sell": "36,500",
      "SellValue": 36500000.0,
      "BuyDiffer": null,
      "BuyDifferValue": 0,
      "SellDiffer": null,
      "SellDifferValue": 0,
      "GroupDate": "/Date(1503016200000)/"
    },
    {
      "Id": 0,
      "TypeName": "Vàng SJC 1L, 10L, 1KG",
      "BranchName": "Hồ Chí Minh",
      "Buy": "36,320",
      "BuyValue": 36320000.0,
      "Sell": "36,520",
      "SellValue": 36520000.0,
      "BuyDiffer": null,
      "BuyDifferValue": 0,
      "SellDiffer": null,
      "SellDifferValue": 0,
      "GroupDate": "/Date(1503021854000)/"
    },
    {
      "Id": 0,
      "TypeName": "Vàng SJC 1L, 10L, 1KG",
      "BranchName": "Hồ Chí Minh",
      "Buy": "36,280",
      "BuyValue": 36280000.0,
      "Sell": "36,480",
      "SellValue": 36480000.0,
      "BuyDiffer": null,
      "BuyDifferValue": 0,
      "SellDiffer": null,
      "SellDifferValue": 0,
      "GroupDate": "/Date(1503081196000)/"
    },
    {
      "Id": 0,
      "TypeName": "Vàng SJC 1L, 10L, 1KG",
      "BranchName": "Hồ Chí Minh",
      "Buy": "36,300",
      "BuyValue": 36300000.0,
      "Sell": "36,500",
      "SellValue": 36500000.0,
      "BuyDiffer": null,
      "BuyDifferValue": 0,
      "SellDiffer": null,
      "SellDifferValue": 0,
      "GroupDate": "/Date(1503084120000)/"
    },
    {
      "Id": 0,
      "TypeName": "Vàng SJC 1L, 10L, 1KG",
      "BranchName": "Hồ Chí Minh",
      "Buy": "36,300",
      "BuyValue": 36300000.0,
      "Sell": "36,500",
      "SellValue": 36500000.0,
      "BuyDiffer": null,
      "BuyDifferValue": 0,
      "SellDiffer": null,
      "SellDifferValue": 0,
      "GroupDate": "/Date(1503253022000)/"
    },
    {
      "Id": 0,
      "TypeName": "Vàng SJC 1L, 10L, 1KG",
      "BranchName": "Hồ Chí Minh",
      "Buy": "36,290",
      "BuyValue": 36290000.0,
      "Sell": "36,490",
      "SellValue": 36490000.0,
      "BuyDiffer": null,
      "BuyDifferValue": 0,
      "SellDiffer": null,
      "SellDifferValue": 0,
      "GroupDate": "/Date(1503257866000)/"
    },
    {
      "Id": 0,
      "TypeName": "Vàng SJC 1L, 10L, 1KG",
      "BranchName": "Hồ Chí Minh",
      "Buy": "36,280",
      "BuyValue": 36280000.0,
      "Sell": "36,480",
      "SellValue": 36480000.0,
      "BuyDiffer": null,
      "BuyDifferValue": 0,
      "SellDiffer": null,
      "SellDifferValue": 0,
      "GroupDate": "/Date(1503261648000)/"
    },
    {
      "Id": 0,
      "TypeName": "Vàng SJC 1L, 10L, 1KG",
      "BranchName": "Hồ Chí Minh",
      "Buy": "36,280",
      "BuyValue": 36280000.0,
      "Sell": "36,480",
      "SellValue": 36480000.0,
      "BuyDiffer": null,
      "BuyDifferValue": 0,
      "SellDiffer": null,
      "SellDifferValue": 0,
      "GroupDate": "/Date(1503339246000)/"
    },
    {
      "Id": 0,
      "TypeName": "Vàng SJC 1L, 10L, 1KG",
      "BranchName": "Hồ Chí Minh",
      "Buy": "36,270",
      "BuyValue": 36270000.0,
      "Sell": "36,470",
      "SellValue": 36470000.0,
      "BuyDiffer": null,
      "BuyDifferValue": 0,
      "SellDiffer": null,
      "SellDifferValue": 0,
      "GroupDate": "/Date(1503347079000)/"
    },
    {
      "Id": 0,
      "TypeName": "Vàng SJC 1L, 10L, 1KG",
      "BranchName": "Hồ Chí Minh",
      "Buy": "36,260",
      "BuyValue": 36260000.0,
      "Sell": "36,460",
      "SellValue": 36460000.0,
      "BuyDiffer": null,
      "BuyDifferValue": 0,
      "SellDiffer": null,
      "SellDifferValue": 0,
      "GroupDate": "/Date(1503349714000)/"
    },
    {
      "Id": 0,
      "TypeName": "Vàng SJC 1L, 10L, 1KG",
      "BranchName": "Hồ Chí Minh",
      "Buy": "36,250",
      "BuyValue": 36250000.0,
      "Sell": "36,450",
      "SellValue": 36450000.0,
      "BuyDiffer": null,
      "BuyDifferValue": 0,
      "SellDiffer": null,
      "SellDifferValue": 0,
      "GroupDate": "/Date(1503360142000)/"
    },
    {
      "Id": 0,
      "TypeName": "Vàng SJC 1L, 10L, 1KG",
      "BranchName": "Hồ Chí Minh",
      "Buy": "36,220",
      "BuyValue": 36220000.0,
      "Sell": "36,420",
      "SellValue": 36420000.0,
      "BuyDiffer": null,
      "BuyDifferValue": 0,
      "SellDiffer": null,
      "SellDifferValue": 0,
      "GroupDate": "/Date(1503425671000)/"
    },
    {
      "Id": 0,
      "TypeName": "Vàng SJC 1L, 10L, 1KG",
      "BranchName": "Hồ Chí Minh",
      "Buy": "36,200",
      "BuyValue": 36200000.0,
      "Sell": "36,400",
      "SellValue": 36400000.0,
      "BuyDiffer": null,
      "BuyDifferValue": 0,
      "SellDiffer": null,
      "SellDifferValue": 0,
      "GroupDate": "/Date(1503430017000)/"
    },
    {
      "Id": 0,
      "TypeName": "Vàng SJC 1L, 10L, 1KG",
      "BranchName": "Hồ Chí Minh",
      "Buy": "36,210",
      "BuyValue": 36210000.0,
      "Sell": "36,410",
      "SellValue": 36410000.0,
      "BuyDiffer": null,
      "BuyDifferValue": 0,
      "SellDiffer": null,
      "SellDifferValue": 0,
      "GroupDate": "/Date(1503433222000)/"
    },
    {
      "Id": 0,
      "TypeName": "Vàng SJC 1L, 10L, 1KG",
      "BranchName": "Hồ Chí Minh",
      "Buy": "36,230",
      "BuyValue": 36230000.0,
      "Sell": "36,430",
      "SellValue": 36430000.0,
      "BuyDiffer": null,
      "BuyDifferValue": 0,
      "SellDiffer": null,
      "SellDifferValue": 0,
      "GroupDate": "/Date(1503445824000)/"
    },
    {
      "Id": 0,
      "TypeName": "Vàng SJC 1L, 10L, 1KG",
      "BranchName": "Hồ Chí Minh",
      "Buy": "36,240",
      "BuyValue": 36240000.0,
      "Sell": "36,440",
      "SellValue": 36440000.0,
      "BuyDiffer": null,
      "BuyDifferValue": 0,
      "SellDiffer": null,
      "SellDifferValue": 0,
      "GroupDate": "/Date(1503511927000)/"
    },
    {
      "Id": 0,
      "TypeName": "Vàng SJC 1L, 10L, 1KG",
      "BranchName": "Hồ Chí Minh",
      "Buy": "36,230",
      "BuyValue": 36230000.0,
      "Sell": "36,430",
      "SellValue": 36430000.0,
      "BuyDiffer": null,
      "BuyDifferValue": 0,
      "SellDiffer": null,
      "SellDifferValue": 0,
      "GroupDate": "/Date(1503521171000)/"
    },
    {
      "Id": 0,
      "TypeName": "Vàng SJC 1L, 10L, 1KG",
      "BranchName": "Hồ Chí Minh",
      "Buy": "36,210",
      "BuyValue": 36210000.0,
      "Sell": "36,410",
      "SellValue": 36410000.0,
      "BuyDiffer": null,
      "BuyDifferValue": 0,
      "SellDiffer": null,
      "SellDifferValue": 0,
      "GroupDate": "/Date(1503534493000)/"
    },
    {
      "Id": 0,
      "TypeName": "Vàng SJC 1L, 10L, 1KG",
      "BranchName": "Hồ Chí Minh",
      "Buy": "36,220",
      "BuyValue": 36220000.0,
      "Sell": "36,420",
      "SellValue": 36420000.0,
      "BuyDiffer": null,
      "BuyDifferValue": 0,
      "SellDiffer": null,
      "SellDifferValue": 0,
      "GroupDate": "/Date(1503537141000)/"
    },
    {
      "Id": 0,
      "TypeName": "Vàng SJC 1L, 10L, 1KG",
      "BranchName": "Hồ Chí Minh",
      "Buy": "36,200",
      "BuyValue": 36200000.0,
      "Sell": "36,400",
      "SellValue": 36400000.0,
      "BuyDiffer": null,
      "BuyDifferValue": 0,
      "SellDiffer": null,
      "SellDifferValue": 0,
      "GroupDate": "/Date(1503599690000)/"
    },
    {
      "Id": 0,
      "TypeName": "Vàng SJC 1L, 10L, 1KG",
      "BranchName": "Hồ Chí Minh",
      "Buy": "36,210",
      "BuyValue": 36210000.0,
      "Sell": "36,410",
      "SellValue": 36410000.0,
      "BuyDiffer": null,
      "BuyDifferValue": 0,
      "SellDiffer": null,
      "SellDifferValue": 0,
      "GroupDate": "/Date(1503605245000)/"
    },
    {
      "Id": 0,
      "TypeName": "Vàng SJC 1L, 10L, 1KG",
      "BranchName": "Hồ Chí Minh",
      "Buy": "36,220",
      "BuyValue": 36220000.0,
      "Sell": "36,420",
      "SellValue": 36420000.0,
      "BuyDiffer": null,
      "BuyDifferValue": 0,
      "SellDiffer": null,
      "SellDifferValue": 0,
      "GroupDate": "/Date(1503606848000)/"
    },
    {
      "Id": 0,
      "TypeName": "Vàng SJC 1L, 10L, 1KG",
      "BranchName": "Hồ Chí Minh",
      "Buy": "36,230",
      "BuyValue": 36230000.0,
      "Sell": "36,430",
      "SellValue": 36430000.0,
      "BuyDiffer": null,
      "BuyDifferValue": 0,
      "SellDiffer": null,
      "SellDifferValue": 0,
      "GroupDate": "/Date(1503618903000)/"
    },
    {
      "Id": 0,
      "TypeName": "Vàng SJC 1L, 10L, 1KG",
      "BranchName": "Hồ Chí Minh",
      "Buy": "36,250",
      "BuyValue": 36250000.0,
      "Sell": "36,450",
      "SellValue": 36450000.0,
      "BuyDiffer": null,
      "BuyDifferValue": 0,
      "SellDiffer": null,
      "SellDifferValue": 0,
      "GroupDate": "/Date(1503624848000)/"
    },
    {
      "Id": 0,
      "TypeName": "Vàng SJC 1L, 10L, 1KG",
      "BranchName": "Hồ Chí Minh",
      "Buy": "36,280",
      "BuyValue": 36280000.0,
      "Sell": "36,480",
      "SellValue": 36480000.0,
      "BuyDiffer": null,
      "BuyDifferValue": 0,
      "SellDiffer": null,
      "SellDifferValue": 0,
      "GroupDate": "/Date(1503685585000)/"
    },
    {
      "Id": 0,
      "TypeName": "Vàng SJC 1L, 10L, 1KG",
      "BranchName": "Hồ Chí Minh",
      "Buy": "36,320",
      "BuyValue": 36320000.0,
      "Sell": "36,520",
      "SellValue": 36520000.0,
      "BuyDiffer": null,
      "BuyDifferValue": 0,
      "SellDiffer": null,
      "SellDifferValue": 0,
      "GroupDate": "/Date(1504124791000)/"
    },
    {
      "Id": 0,
      "TypeName": "Vàng SJC 1L, 10L, 1KG",
      "BranchName": "Hồ Chí Minh",
      "Buy": "36,330",
      "BuyValue": 36330000.0,
      "Sell": "36,530",
      "SellValue": 36530000.0,
      "BuyDiffer": null,
      "BuyDifferValue": 0,
      "SellDiffer": null,
      "SellDifferValue": 0,
      "GroupDate": "/Date(1504125507000)/"
    },
    {
      "Id": 0,
      "TypeName": "Vàng SJC 1L, 10L, 1KG",
      "BranchName": "Hồ Chí Minh",
      "Buy": "36,340",
      "BuyValue": 36340000.0,
      "Sell": "36,540",
      "SellValue": 36540000.0,
      "BuyDiffer": null,
      "BuyDifferValue": 0,
      "SellDiffer": null,
      "SellDifferValue": 0,
      "GroupDate": "/Date(1504135266000)/"
    },
    {
      "Id": 0,
      "TypeName": "Vàng SJC 1L, 10L, 1KG",
      "BranchName": "Hồ Chí Minh",
      "Buy": "36,350",
      "BuyValue": 36350000.0,
      "Sell": "36,550",
      "SellValue": 36550000.0,
      "BuyDiffer": null,
      "BuyDifferValue": 0,
      "SellDiffer": null,
      "SellDifferValue": 0,
      "GroupDate": "/Date(1504137467000)/"
    },
    {
      "Id": 0,
      "TypeName": "Vàng SJC 1L, 10L, 1KG",
      "BranchName": "Hồ Chí Minh",
      "Buy": "36,360",
      "BuyValue": 36360000.0,
      "Sell": "36,560",
      "SellValue": 36560000.0,
      "BuyDiffer": null,
      "BuyDifferValue": 0,
      "SellDiffer": null,
      "SellDifferValue": 0,
      "GroupDate": "/Date(1504138371000)/"
    },
    {
      "Id": 0,
      "TypeName": "Vàng SJC 1L, 10L, 1KG",
      "BranchName": "Hồ Chí Minh",
      "Buy": "36,460",
      "BuyValue": 36460000.0,
      "Sell": "36,660",
      "SellValue": 36660000.0,
      "BuyDiffer": null,
      "BuyDifferValue": 0,
      "SellDiffer": null,
      "SellDifferValue": 0,
      "GroupDate": "/Date(1504203627000)/"
    },
    {
      "Id": 0,
      "TypeName": "Vàng SJC 1L, 10L, 1KG",
      "BranchName": "Hồ Chí Minh",
      "Buy": "36,450",
      "BuyValue": 36450000.0,
      "Sell": "36,650",
      "SellValue": 36650000.0,
      "BuyDiffer": null,
      "BuyDifferValue": 0,
      "SellDiffer": null,
      "SellDifferValue": 0,
      "GroupDate": "/Date(1504204166000)/"
    },
    {
      "Id": 0,
      "TypeName": "Vàng SJC 1L, 10L, 1KG",
      "BranchName": "Hồ Chí Minh",
      "Buy": "36,430",
      "BuyValue": 36430000.0,
      "Sell": "36,630",
      "SellValue": 36630000.0,
      "BuyDiffer": null,
      "BuyDifferValue": 0,
      "SellDiffer": null,
      "SellDifferValue": 0,
      "GroupDate": "/Date(1504214137000)/"
    },
    {
      "Id": 0,
      "TypeName": "Vàng SJC 1L, 10L, 1KG",
      "BranchName": "Hồ Chí Minh",
      "Buy": "36,450",
      "BuyValue": 36450000.0,
      "Sell": "36,650",
      "SellValue": 36650000.0,
      "BuyDiffer": null,
      "BuyDifferValue": 0,
      "SellDiffer": null,
      "SellDifferValue": 0,
      "GroupDate": "/Date(1504229527000)/"
    },
    {
      "Id": 0,
      "TypeName": "Vàng SJC 1L, 10L, 1KG",
      "BranchName": "Hồ Chí Minh",
      "Buy": "36,600",
      "BuyValue": 36600000.0,
      "Sell": "36,850",
      "SellValue": 36850000.0,
      "BuyDiffer": null,
      "BuyDifferValue": 0,
      "SellDiffer": null,
      "SellDifferValue": 0,
      "GroupDate": "/Date(1504464098000)/"
    },
    {
      "Id": 0,
      "TypeName": "Vàng SJC 1L, 10L, 1KG",
      "BranchName": "Hồ Chí Minh",
      "Buy": "36,650",
      "BuyValue": 36650000.0,
      "Sell": "36,850",
      "SellValue": 36850000.0,
      "BuyDiffer": null,
      "BuyDifferValue": 0,
      "SellDiffer": null,
      "SellDifferValue": 0,
      "GroupDate": "/Date(1504549459000)/"
    },
    {
      "Id": 0,
      "TypeName": "Vàng SJC 1L, 10L, 1KG",
      "BranchName": "Hồ Chí Minh",
      "Buy": "36,630",
      "BuyValue": 36630000.0,
      "Sell": "36,830",
      "SellValue": 36830000.0,
      "BuyDiffer": null,
      "BuyDifferValue": 0,
      "SellDiffer": null,
      "SellDifferValue": 0,
      "GroupDate": "/Date(1504549624000)/"
    },
    {
      "Id": 0,
      "TypeName": "Vàng SJC 1L, 10L, 1KG",
      "BranchName": "Hồ Chí Minh",
      "Buy": "36,650",
      "BuyValue": 36650000.0,
      "Sell": "36,850",
      "SellValue": 36850000.0,
      "BuyDiffer": null,
      "BuyDifferValue": 0,
      "SellDiffer": null,
      "SellDifferValue": 0,
      "GroupDate": "/Date(1504550808000)/"
    },
    {
      "Id": 0,
      "TypeName": "Vàng SJC 1L, 10L, 1KG",
      "BranchName": "Hồ Chí Minh",
      "Buy": "36,670",
      "BuyValue": 36670000.0,
      "Sell": "36,870",
      "SellValue": 36870000.0,
      "BuyDiffer": null,
      "BuyDifferValue": 0,
      "SellDiffer": null,
      "SellDifferValue": 0,
      "GroupDate": "/Date(1504553130000)/"
    },
    {
      "Id": 0,
      "TypeName": "Vàng SJC 1L, 10L, 1KG",
      "BranchName": "Hồ Chí Minh",
      "Buy": "36,680",
      "BuyValue": 36680000.0,
      "Sell": "36,880",
      "SellValue": 36880000.0,
      "BuyDiffer": null,
      "BuyDifferValue": 0,
      "SellDiffer": null,
      "SellDifferValue": 0,
      "GroupDate": "/Date(1504553401000)/"
    },
    {
      "Id": 0,
      "TypeName": "Vàng SJC 1L, 10L, 1KG",
      "BranchName": "Hồ Chí Minh",
      "Buy": "36,690",
      "BuyValue": 36690000.0,
      "Sell": "36,890",
      "SellValue": 36890000.0,
      "BuyDiffer": null,
      "BuyDifferValue": 0,
      "SellDiffer": null,
      "SellDifferValue": 0,
      "GroupDate": "/Date(1504553599000)/"
    },
    {
      "Id": 0,
      "TypeName": "Vàng SJC 1L, 10L, 1KG",
      "BranchName": "Hồ Chí Minh",
      "Buy": "36,670",
      "BuyValue": 36670000.0,
      "Sell": "36,870",
      "SellValue": 36870000.0,
      "BuyDiffer": null,
      "BuyDifferValue": 0,
      "SellDiffer": null,
      "SellDifferValue": 0,
      "GroupDate": "/Date(1504554054000)/"
    },
    {
      "Id": 0,
      "TypeName": "Vàng SJC 1L, 10L, 1KG",
      "BranchName": "Hồ Chí Minh",
      "Buy": "36,660",
      "BuyValue": 36660000.0,
      "Sell": "36,860",
      "SellValue": 36860000.0,
      "BuyDiffer": null,
      "BuyDifferValue": 0,
      "SellDiffer": null,
      "SellDifferValue": 0,
      "GroupDate": "/Date(1504555094000)/"
    },
    {
      "Id": 0,
      "TypeName": "Vàng SJC 1L, 10L, 1KG",
      "BranchName": "Hồ Chí Minh",
      "Buy": "36,680",
      "BuyValue": 36680000.0,
      "Sell": "36,880",
      "SellValue": 36880000.0,
      "BuyDiffer": null,
      "BuyDifferValue": 0,
      "SellDiffer": null,
      "SellDifferValue": 0,
      "GroupDate": "/Date(1504556989000)/"
    },
    {
      "Id": 0,
      "TypeName": "Vàng SJC 1L, 10L, 1KG",
      "BranchName": "Hồ Chí Minh",
      "Buy": "36,670",
      "BuyValue": 36670000.0,
      "Sell": "36,870",
      "SellValue": 36870000.0,
      "BuyDiffer": null,
      "BuyDifferValue": 0,
      "SellDiffer": null,
      "SellDifferValue": 0,
      "GroupDate": "/Date(1504558056000)/"
    },
    {
      "Id": 0,
      "TypeName": "Vàng SJC 1L, 10L, 1KG",
      "BranchName": "Hồ Chí Minh",
      "Buy": "36,660",
      "BuyValue": 36660000.0,
      "Sell": "36,860",
      "SellValue": 36860000.0,
      "BuyDiffer": null,
      "BuyDifferValue": 0,
      "SellDiffer": null,
      "SellDifferValue": 0,
      "GroupDate": "/Date(1504567009000)/"
    },
    {
      "Id": 0,
      "TypeName": "Vàng SJC 1L, 10L, 1KG",
      "BranchName": "Hồ Chí Minh",
      "Buy": "36,650",
      "BuyValue": 36650000.0,
      "Sell": "36,850",
      "SellValue": 36850000.0,
      "BuyDiffer": null,
      "BuyDifferValue": 0,
      "SellDiffer": null,
      "SellDifferValue": 0,
      "GroupDate": "/Date(1504572122000)/"
    },
    {
      "Id": 0,
      "TypeName": "Vàng SJC 1L, 10L, 1KG",
      "BranchName": "Hồ Chí Minh",
      "Buy": "36,640",
      "BuyValue": 36640000.0,
      "Sell": "36,840",
      "SellValue": 36840000.0,
      "BuyDiffer": null,
      "BuyDifferValue": 0,
      "SellDiffer": null,
      "SellDifferValue": 0,
      "GroupDate": "/Date(1504572576000)/"
    },
    {
      "Id": 0,
      "TypeName": "Vàng SJC 1L, 10L, 1KG",
      "BranchName": "Hồ Chí Minh",
      "Buy": "36,620",
      "BuyValue": 36620000.0,
      "Sell": "36,820",
      "SellValue": 36820000.0,
      "BuyDiffer": null,
      "BuyDifferValue": 0,
      "SellDiffer": null,
      "SellDifferValue": 0,
      "GroupDate": "/Date(1504574640000)/"
    },
    {
      "Id": 0,
      "TypeName": "Vàng SJC 1L, 10L, 1KG",
      "BranchName": "Hồ Chí Minh",
      "Buy": "36,600",
      "BuyValue": 36600000.0,
      "Sell": "36,800",
      "SellValue": 36800000.0,
      "BuyDiffer": null,
      "BuyDifferValue": 0,
      "SellDiffer": null,
      "SellDifferValue": 0,
      "GroupDate": "/Date(1504576111000)/"
    },
    {
      "Id": 0,
      "TypeName": "Vàng SJC 1L, 10L, 1KG",
      "BranchName": "Hồ Chí Minh",
      "Buy": "36,580",
      "BuyValue": 36580000.0,
      "Sell": "36,780",
      "SellValue": 36780000.0,
      "BuyDiffer": null,
      "BuyDifferValue": 0,
      "SellDiffer": null,
      "SellDifferValue": 0,
      "GroupDate": "/Date(1504577347000)/"
    },
    {
      "Id": 0,
      "TypeName": "Vàng SJC 1L, 10L, 1KG",
      "BranchName": "Hồ Chí Minh",
      "Buy": "36,650",
      "BuyValue": 36650000.0,
      "Sell": "36,850",
      "SellValue": 36850000.0,
      "BuyDiffer": null,
      "BuyDifferValue": 0,
      "SellDiffer": null,
      "SellDifferValue": 0,
      "GroupDate": "/Date(1504635626000)/"
    },
    {
      "Id": 0,
      "TypeName": "Vàng SJC 1L, 10L, 1KG",
      "BranchName": "Hồ Chí Minh",
      "Buy": "36,660",
      "BuyValue": 36660000.0,
      "Sell": "36,860",
      "SellValue": 36860000.0,
      "BuyDiffer": null,
      "BuyDifferValue": 0,
      "SellDiffer": null,
      "SellDifferValue": 0,
      "GroupDate": "/Date(1504635822000)/"
    },
    {
      "Id": 0,
      "TypeName": "Vàng SJC 1L, 10L, 1KG",
      "BranchName": "Hồ Chí Minh",
      "Buy": "36,670",
      "BuyValue": 36670000.0,
      "Sell": "36,870",
      "SellValue": 36870000.0,
      "BuyDiffer": null,
      "BuyDifferValue": 0,
      "SellDiffer": null,
      "SellDifferValue": 0,
      "GroupDate": "/Date(1504636767000)/"
    },
    {
      "Id": 0,
      "TypeName": "Vàng SJC 1L, 10L, 1KG",
      "BranchName": "Hồ Chí Minh",
      "Buy": "36,680",
      "BuyValue": 36680000.0,
      "Sell": "36,880",
      "SellValue": 36880000.0,
      "BuyDiffer": null,
      "BuyDifferValue": 0,
      "SellDiffer": null,
      "SellDifferValue": 0,
      "GroupDate": "/Date(1504639230000)/"
    },
    {
      "Id": 0,
      "TypeName": "Vàng SJC 1L, 10L, 1KG",
      "BranchName": "Hồ Chí Minh",
      "Buy": "36,690",
      "BuyValue": 36690000.0,
      "Sell": "36,890",
      "SellValue": 36890000.0,
      "BuyDiffer": null,
      "BuyDifferValue": 0,
      "SellDiffer": null,
      "SellDifferValue": 0,
      "GroupDate": "/Date(1504639484000)/"
    },
    {
      "Id": 0,
      "TypeName": "Vàng SJC 1L, 10L, 1KG",
      "BranchName": "Hồ Chí Minh",
      "Buy": "36,700",
      "BuyValue": 36700000.0,
      "Sell": "36,900",
      "SellValue": 36900000.0,
      "BuyDiffer": null,
      "BuyDifferValue": 0,
      "SellDiffer": null,
      "SellDifferValue": 0,
      "GroupDate": "/Date(1504640840000)/"
    },
    {
      "Id": 0,
      "TypeName": "Vàng SJC 1L, 10L, 1KG",
      "BranchName": "Hồ Chí Minh",
      "Buy": "36,730",
      "BuyValue": 36730000.0,
      "Sell": "36,930",
      "SellValue": 36930000.0,
      "BuyDiffer": null,
      "BuyDifferValue": 0,
      "SellDiffer": null,
      "SellDifferValue": 0,
      "GroupDate": "/Date(1504641176000)/"
    },
    {
      "Id": 0,
      "TypeName": "Vàng SJC 1L, 10L, 1KG",
      "BranchName": "Hồ Chí Minh",
      "Buy": "36,710",
      "BuyValue": 36710000.0,
      "Sell": "36,910",
      "SellValue": 36910000.0,
      "BuyDiffer": null,
      "BuyDifferValue": 0,
      "SellDiffer": null,
      "SellDifferValue": 0,
      "GroupDate": "/Date(1504642171000)/"
    },
    {
      "Id": 0,
      "TypeName": "Vàng SJC 1L, 10L, 1KG",
      "BranchName": "Hồ Chí Minh",
      "Buy": "36,720",
      "BuyValue": 36720000.0,
      "Sell": "36,920",
      "SellValue": 36920000.0,
      "BuyDiffer": null,
      "BuyDifferValue": 0,
      "SellDiffer": null,
      "SellDifferValue": 0,
      "GroupDate": "/Date(1504656909000)/"
    },
    {
      "Id": 0,
      "TypeName": "Vàng SJC 1L, 10L, 1KG",
      "BranchName": "Hồ Chí Minh",
      "Buy": "36,730",
      "BuyValue": 36730000.0,
      "Sell": "36,930",
      "SellValue": 36930000.0,
      "BuyDiffer": null,
      "BuyDifferValue": 0,
      "SellDiffer": null,
      "SellDifferValue": 0,
      "GroupDate": "/Date(1504657070000)/"
    },
    {
      "Id": 0,
      "TypeName": "Vàng SJC 1L, 10L, 1KG",
      "BranchName": "Hồ Chí Minh",
      "Buy": "36,740",
      "BuyValue": 36740000.0,
      "Sell": "36,940",
      "SellValue": 36940000.0,
      "BuyDiffer": null,
      "BuyDifferValue": 0,
      "SellDiffer": null,
      "SellDifferValue": 0,
      "GroupDate": "/Date(1504657978000)/"
    },
    {
      "Id": 0,
      "TypeName": "Vàng SJC 1L, 10L, 1KG",
      "BranchName": "Hồ Chí Minh",
      "Buy": "36,750",
      "BuyValue": 36750000.0,
      "Sell": "36,950",
      "SellValue": 36950000.0,
      "BuyDiffer": null,
      "BuyDifferValue": 0,
      "SellDiffer": null,
      "SellDifferValue": 0,
      "GroupDate": "/Date(1504658186000)/"
    },
    {
      "Id": 0,
      "TypeName": "Vàng SJC 1L, 10L, 1KG",
      "BranchName": "Hồ Chí Minh",
      "Buy": "36,770",
      "BuyValue": 36770000.0,
      "Sell": "36,970",
      "SellValue": 36970000.0,
      "BuyDiffer": null,
      "BuyDifferValue": 0,
      "SellDiffer": null,
      "SellDifferValue": 0,
      "GroupDate": "/Date(1504659148000)/"
    },
    {
      "Id": 0,
      "TypeName": "Vàng SJC 1L, 10L, 1KG",
      "BranchName": "Hồ Chí Minh",
      "Buy": "36,800",
      "BuyValue": 36800000.0,
      "Sell": "37,000",
      "SellValue": 37000000.0,
      "BuyDiffer": null,
      "BuyDifferValue": 0,
      "SellDiffer": null,
      "SellDifferValue": 0,
      "GroupDate": "/Date(1504660547000)/"
    },
    {
      "Id": 0,
      "TypeName": "Vàng SJC 1L, 10L, 1KG",
      "BranchName": "Hồ Chí Minh",
      "Buy": "36,820",
      "BuyValue": 36820000.0,
      "Sell": "37,020",
      "SellValue": 37020000.0,
      "BuyDiffer": null,
      "BuyDifferValue": 0,
      "SellDiffer": null,
      "SellDifferValue": 0,
      "GroupDate": "/Date(1504663118000)/"
    },
    {
      "Id": 0,
      "TypeName": "Vàng SJC 1L, 10L, 1KG",
      "BranchName": "Hồ Chí Minh",
      "Buy": "36,830",
      "BuyValue": 36830000.0,
      "Sell": "37,030",
      "SellValue": 37030000.0,
      "BuyDiffer": null,
      "BuyDifferValue": 0,
      "SellDiffer": null,
      "SellDifferValue": 0,
      "GroupDate": "/Date(1504663170000)/"
    },
    {
      "Id": 0,
      "TypeName": "Vàng SJC 1L, 10L, 1KG",
      "BranchName": "Hồ Chí Minh",
      "Buy": "36,850",
      "BuyValue": 36850000.0,
      "Sell": "37,050",
      "SellValue": 37050000.0,
      "BuyDiffer": null,
      "BuyDifferValue": 0,
      "SellDiffer": null,
      "SellDifferValue": 0,
      "GroupDate": "/Date(1504663831000)/"
    },
    {
      "Id": 0,
      "TypeName": "Vàng SJC 1L, 10L, 1KG",
      "BranchName": "Hồ Chí Minh",
      "Buy": "36,800",
      "BuyValue": 36800000.0,
      "Sell": "37,000",
      "SellValue": 37000000.0,
      "BuyDiffer": null,
      "BuyDifferValue": 0,
      "SellDiffer": null,
      "SellDifferValue": 0,
      "GroupDate": "/Date(1504721909000)/"
    },
    {
      "Id": 0,
      "TypeName": "Vàng SJC 1L, 10L, 1KG",
      "BranchName": "Hồ Chí Minh",
      "Buy": "36,820",
      "BuyValue": 36820000.0,
      "Sell": "37,020",
      "SellValue": 37020000.0,
      "BuyDiffer": null,
      "BuyDifferValue": 0,
      "SellDiffer": null,
      "SellDifferValue": 0,
      "GroupDate": "/Date(1504723253000)/"
    },
    {
      "Id": 0,
      "TypeName": "Vàng SJC 1L, 10L, 1KG",
      "BranchName": "Hồ Chí Minh",
      "Buy": "36,820",
      "BuyValue": 36820000.0,
      "Sell": "37,020",
      "SellValue": 37020000.0,
      "BuyDiffer": null,
      "BuyDifferValue": 0,
      "SellDiffer": null,
      "SellDifferValue": 0,
      "GroupDate": "/Date(1504723271000)/"
    },
    {
      "Id": 0,
      "TypeName": "Vàng SJC 1L, 10L, 1KG",
      "BranchName": "Hồ Chí Minh",
      "Buy": "36,830",
      "BuyValue": 36830000.0,
      "Sell": "37,030",
      "SellValue": 37030000.0,
      "BuyDiffer": null,
      "BuyDifferValue": 0,
      "SellDiffer": null,
      "SellDifferValue": 0,
      "GroupDate": "/Date(1504723456000)/"
    },
    {
      "Id": 0,
      "TypeName": "Vàng SJC 1L, 10L, 1KG",
      "BranchName": "Hồ Chí Minh",
      "Buy": "37,060",
      "BuyValue": 37060000.0,
      "Sell": "37,280",
      "SellValue": 37280000.0,
      "BuyDiffer": null,
      "BuyDifferValue": 0,
      "SellDiffer": null,
      "SellDifferValue": 0,
      "GroupDate": "/Date(1504830499000)/"
    },
    {
      "Id": 0,
      "TypeName": "Vàng SJC 1L, 10L, 1KG",
      "BranchName": "Hồ Chí Minh",
      "Buy": "37,040",
      "BuyValue": 37040000.0,
      "Sell": "37,260",
      "SellValue": 37260000.0,
      "BuyDiffer": null,
      "BuyDifferValue": 0,
      "SellDiffer": null,
      "SellDifferValue": 0,
      "GroupDate": "/Date(1504830952000)/"
    },
    {
      "Id": 0,
      "TypeName": "Vàng SJC 1L, 10L, 1KG",
      "BranchName": "Hồ Chí Minh",
      "Buy": "37,080",
      "BuyValue": 37080000.0,
      "Sell": "37,300",
      "SellValue": 37300000.0,
      "BuyDiffer": null,
      "BuyDifferValue": 0,
      "SellDiffer": null,
      "SellDifferValue": 0,
      "GroupDate": "/Date(1504832019000)/"
    },
    {
      "Id": 0,
      "TypeName": "Vàng SJC 1L, 10L, 1KG",
      "BranchName": "Hồ Chí Minh",
      "Buy": "37,060",
      "BuyValue": 37060000.0,
      "Sell": "37,280",
      "SellValue": 37280000.0,
      "BuyDiffer": null,
      "BuyDifferValue": 0,
      "SellDiffer": null,
      "SellDifferValue": 0,
      "GroupDate": "/Date(1504832859000)/"
    },
    {
      "Id": 0,
      "TypeName": "Vàng SJC 1L, 10L, 1KG",
      "BranchName": "Hồ Chí Minh",
      "Buy": "37,000",
      "BuyValue": 37000000.0,
      "Sell": "37,220",
      "SellValue": 37220000.0,
      "BuyDiffer": null,
      "BuyDifferValue": 0,
      "SellDiffer": null,
      "SellDifferValue": 0,
      "GroupDate": "/Date(1504895458000)/"
    },
    {
      "Id": 0,
      "TypeName": "Vàng SJC 1L, 10L, 1KG",
      "BranchName": "Hồ Chí Minh",
      "Buy": "36,980",
      "BuyValue": 36980000.0,
      "Sell": "37,200",
      "SellValue": 37200000.0,
      "BuyDiffer": null,
      "BuyDifferValue": 0,
      "SellDiffer": null,
      "SellDifferValue": 0,
      "GroupDate": "/Date(1504896403000)/"
    },
    {
      "Id": 0,
      "TypeName": "Vàng SJC 1L, 10L, 1KG",
      "BranchName": "Hồ Chí Minh",
      "Buy": "36,960",
      "BuyValue": 36960000.0,
      "Sell": "37,180",
      "SellValue": 37180000.0,
      "BuyDiffer": null,
      "BuyDifferValue": 0,
      "SellDiffer": null,
      "SellDifferValue": 0,
      "GroupDate": "/Date(1504900911000)/"
    },
    {
      "Id": 0,
      "TypeName": "Vàng SJC 1L, 10L, 1KG",
      "BranchName": "Hồ Chí Minh",
      "Buy": "36,940",
      "BuyValue": 36940000.0,
      "Sell": "37,160",
      "SellValue": 37160000.0,
      "BuyDiffer": null,
      "BuyDifferValue": 0,
      "SellDiffer": null,
      "SellDifferValue": 0,
      "GroupDate": "/Date(1504903759000)/"
    },
    {
      "Id": 0,
      "TypeName": "Vàng SJC 1L, 10L, 1KG",
      "BranchName": "Hồ Chí Minh",
      "Buy": "36,830",
      "BuyValue": 36830000.0,
      "Sell": "37,030",
      "SellValue": 37030000.0,
      "BuyDiffer": null,
      "BuyDifferValue": 0,
      "SellDiffer": null,
      "SellDifferValue": 0,
      "GroupDate": "/Date(1505067206000)/"
    },
    {
      "Id": 0,
      "TypeName": "Vàng SJC 1L, 10L, 1KG",
      "BranchName": "Hồ Chí Minh",
      "Buy": "36,850",
      "BuyValue": 36850000.0,
      "Sell": "37,050",
      "SellValue": 37050000.0,
      "BuyDiffer": null,
      "BuyDifferValue": 0,
      "SellDiffer": null,
      "SellDifferValue": 0,
      "GroupDate": "/Date(1505068422000)/"
    },
    {
      "Id": 0,
      "TypeName": "Vàng SJC 1L, 10L, 1KG",
      "BranchName": "Hồ Chí Minh",
      "Buy": "36,800",
      "BuyValue": 36800000.0,
      "Sell": "37,000",
      "SellValue": 37000000.0,
      "BuyDiffer": null,
      "BuyDifferValue": 0,
      "SellDiffer": null,
      "SellDifferValue": 0,
      "GroupDate": "/Date(1505069095000)/"
    },
    {
      "Id": 0,
      "TypeName": "Vàng SJC 1L, 10L, 1KG",
      "BranchName": "Hồ Chí Minh",
      "Buy": "36,830",
      "BuyValue": 36830000.0,
      "Sell": "37,030",
      "SellValue": 37030000.0,
      "BuyDiffer": null,
      "BuyDifferValue": 0,
      "SellDiffer": null,
      "SellDifferValue": 0,
      "GroupDate": "/Date(1505073095000)/"
    },
    {
      "Id": 0,
      "TypeName": "Vàng SJC 1L, 10L, 1KG",
      "BranchName": "Hồ Chí Minh",
      "Buy": "36,810",
      "BuyValue": 36810000.0,
      "Sell": "37,010",
      "SellValue": 37010000.0,
      "BuyDiffer": null,
      "BuyDifferValue": 0,
      "SellDiffer": null,
      "SellDifferValue": 0,
      "GroupDate": "/Date(1505075045000)/"
    },
    {
      "Id": 0,
      "TypeName": "Vàng SJC 1L, 10L, 1KG",
      "BranchName": "Hồ Chí Minh",
      "Buy": "36,800",
      "BuyValue": 36800000.0,
      "Sell": "37,000",
      "SellValue": 37000000.0,
      "BuyDiffer": null,
      "BuyDifferValue": 0,
      "SellDiffer": null,
      "SellDifferValue": 0,
      "GroupDate": "/Date(1505086595000)/"
    },
    {
      "Id": 0,
      "TypeName": "Vàng SJC 1L, 10L, 1KG",
      "BranchName": "Hồ Chí Minh",
      "Buy": "36,780",
      "BuyValue": 36780000.0,
      "Sell": "36,980",
      "SellValue": 36980000.0,
      "BuyDiffer": null,
      "BuyDifferValue": 0,
      "SellDiffer": null,
      "SellDifferValue": 0,
      "GroupDate": "/Date(1505087500000)/"
    },
    {
      "Id": 0,
      "TypeName": "Vàng SJC 1L, 10L, 1KG",
      "BranchName": "Hồ Chí Minh",
      "Buy": "36,760",
      "BuyValue": 36760000.0,
      "Sell": "36,960",
      "SellValue": 36960000.0,
      "BuyDiffer": null,
      "BuyDifferValue": 0,
      "SellDiffer": null,
      "SellDifferValue": 0,
      "GroupDate": "/Date(1505094072000)/"
    },
    {
      "Id": 0,
      "TypeName": "Vàng SJC 1L, 10L, 1KG",
      "BranchName": "Hồ Chí Minh",
      "Buy": "36,780",
      "BuyValue": 36780000.0,
      "Sell": "36,980",
      "SellValue": 36980000.0,
      "BuyDiffer": null,
      "BuyDifferValue": 0,
      "SellDiffer": null,
      "SellDifferValue": 0,
      "GroupDate": "/Date(1505096814000)/"
    },
    {
      "Id": 0,
      "TypeName": "Vàng SJC 1L, 10L, 1KG",
      "BranchName": "Hồ Chí Minh",
      "Buy": "36,650",
      "BuyValue": 36650000.0,
      "Sell": "36,850",
      "SellValue": 36850000.0,
      "BuyDiffer": null,
      "BuyDifferValue": 0,
      "SellDiffer": null,
      "SellDifferValue": 0,
      "GroupDate": "/Date(1505154103000)/"
    },
    {
      "Id": 0,
      "TypeName": "Vàng SJC 1L, 10L, 1KG",
      "BranchName": "Hồ Chí Minh",
      "Buy": "36,630",
      "BuyValue": 36630000.0,
      "Sell": "36,830",
      "SellValue": 36830000.0,
      "BuyDiffer": null,
      "BuyDifferValue": 0,
      "SellDiffer": null,
      "SellDifferValue": 0,
      "GroupDate": "/Date(1505154374000)/"
    },
    {
      "Id": 0,
      "TypeName": "Vàng SJC 1L, 10L, 1KG",
      "BranchName": "Hồ Chí Minh",
      "Buy": "36,600",
      "BuyValue": 36600000.0,
      "Sell": "36,800",
      "SellValue": 36800000.0,
      "BuyDiffer": null,
      "BuyDifferValue": 0,
      "SellDiffer": null,
      "SellDifferValue": 0,
      "GroupDate": "/Date(1505156233000)/"
    },
    {
      "Id": 0,
      "TypeName": "Vàng SJC 1L, 10L, 1KG",
      "BranchName": "Hồ Chí Minh",
      "Buy": "36,600",
      "BuyValue": 36600000.0,
      "Sell": "36,800",
      "SellValue": 36800000.0,
      "BuyDiffer": null,
      "BuyDifferValue": 0,
      "SellDiffer": null,
      "SellDifferValue": 0,
      "GroupDate": "/Date(1505156238000)/"
    },
    {
      "Id": 0,
      "TypeName": "Vàng SJC 1L, 10L, 1KG",
      "BranchName": "Hồ Chí Minh",
      "Buy": "36,580",
      "BuyValue": 36580000.0,
      "Sell": "36,780",
      "SellValue": 36780000.0,
      "BuyDiffer": null,
      "BuyDifferValue": 0,
      "SellDiffer": null,
      "SellDifferValue": 0,
      "GroupDate": "/Date(1505156567000)/"
    },
    {
      "Id": 0,
      "TypeName": "Vàng SJC 1L, 10L, 1KG",
      "BranchName": "Hồ Chí Minh",
      "Buy": "36,560",
      "BuyValue": 36560000.0,
      "Sell": "36,760",
      "SellValue": 36760000.0,
      "BuyDiffer": null,
      "BuyDifferValue": 0,
      "SellDiffer": null,
      "SellDifferValue": 0,
      "GroupDate": "/Date(1505156890000)/"
    },
    {
      "Id": 0,
      "TypeName": "Vàng SJC 1L, 10L, 1KG",
      "BranchName": "Hồ Chí Minh",
      "Buy": "36,550",
      "BuyValue": 36550000.0,
      "Sell": "36,750",
      "SellValue": 36750000.0,
      "BuyDiffer": null,
      "BuyDifferValue": 0,
      "SellDiffer": null,
      "SellDifferValue": 0,
      "GroupDate": "/Date(1505161719000)/"
    },
    {
      "Id": 0,
      "TypeName": "Vàng SJC 1L, 10L, 1KG",
      "BranchName": "Hồ Chí Minh",
      "Buy": "36,530",
      "BuyValue": 36530000.0,
      "Sell": "36,730",
      "SellValue": 36730000.0,
      "BuyDiffer": null,
      "BuyDifferValue": 0,
      "SellDiffer": null,
      "SellDifferValue": 0,
      "GroupDate": "/Date(1505162934000)/"
    },
    {
      "Id": 0,
      "TypeName": "Vàng SJC 1L, 10L, 1KG",
      "BranchName": "Hồ Chí Minh",
      "Buy": "36,550",
      "BuyValue": 36550000.0,
      "Sell": "36,750",
      "SellValue": 36750000.0,
      "BuyDiffer": null,
      "BuyDifferValue": 0,
      "SellDiffer": null,
      "SellDifferValue": 0,
      "GroupDate": "/Date(1505172891000)/"
    },
    {
      "Id": 0,
      "TypeName": "Vàng SJC 1L, 10L, 1KG",
      "BranchName": "Hồ Chí Minh",
      "Buy": "36,530",
      "BuyValue": 36530000.0,
      "Sell": "36,730",
      "SellValue": 36730000.0,
      "BuyDiffer": null,
      "BuyDifferValue": 0,
      "SellDiffer": null,
      "SellDifferValue": 0,
      "GroupDate": "/Date(1505175111000)/"
    },
    {
      "Id": 0,
      "TypeName": "Vàng SJC 1L, 10L, 1KG",
      "BranchName": "Hồ Chí Minh",
      "Buy": "36,560",
      "BuyValue": 36560000.0,
      "Sell": "36,760",
      "SellValue": 36760000.0,
      "BuyDiffer": null,
      "BuyDifferValue": 0,
      "SellDiffer": null,
      "SellDifferValue": 0,
      "GroupDate": "/Date(1505178861000)/"
    },
    {
      "Id": 0,
      "TypeName": "Vàng SJC 1L, 10L, 1KG",
      "BranchName": "Hồ Chí Minh",
      "Buy": "36,540",
      "BuyValue": 36540000.0,
      "Sell": "36,740",
      "SellValue": 36740000.0,
      "BuyDiffer": null,
      "BuyDifferValue": 0,
      "SellDiffer": null,
      "SellDifferValue": 0,
      "GroupDate": "/Date(1505182198000)/"
    },
    {
      "Id": 0,
      "TypeName": "Vàng SJC 1L, 10L, 1KG",
      "BranchName": "Hồ Chí Minh",
      "Buy": "36,580",
      "BuyValue": 36580000.0,
      "Sell": "36,780",
      "SellValue": 36780000.0,
      "BuyDiffer": null,
      "BuyDifferValue": 0,
      "SellDiffer": null,
      "SellDifferValue": 0,
      "GroupDate": "/Date(1505240037000)/"
    },
    {
      "Id": 0,
      "TypeName": "Vàng SJC 1L, 10L, 1KG",
      "BranchName": "Hồ Chí Minh",
      "Buy": "36,560",
      "BuyValue": 36560000.0,
      "Sell": "36,760",
      "SellValue": 36760000.0,
      "BuyDiffer": null,
      "BuyDifferValue": 0,
      "SellDiffer": null,
      "SellDifferValue": 0,
      "GroupDate": "/Date(1505241305000)/"
    },
    {
      "Id": 0,
      "TypeName": "Vàng SJC 1L, 10L, 1KG",
      "BranchName": "Hồ Chí Minh",
      "Buy": "36,550",
      "BuyValue": 36550000.0,
      "Sell": "36,750",
      "SellValue": 36750000.0,
      "BuyDiffer": null,
      "BuyDifferValue": 0,
      "SellDiffer": null,
      "SellDifferValue": 0,
      "GroupDate": "/Date(1505250674000)/"
    },
    {
      "Id": 0,
      "TypeName": "Vàng SJC 1L, 10L, 1KG",
      "BranchName": "Hồ Chí Minh",
      "Buy": "36,550",
      "BuyValue": 36550000.0,
      "Sell": "36,750",
      "SellValue": 36750000.0,
      "BuyDiffer": null,
      "BuyDifferValue": 0,
      "SellDiffer": null,
      "SellDifferValue": 0,
      "GroupDate": "/Date(1505250713000)/"
    },
    {
      "Id": 0,
      "TypeName": "Vàng SJC 1L, 10L, 1KG",
      "BranchName": "Hồ Chí Minh",
      "Buy": "36,560",
      "BuyValue": 36560000.0,
      "Sell": "36,760",
      "SellValue": 36760000.0,
      "BuyDiffer": null,
      "BuyDifferValue": 0,
      "SellDiffer": null,
      "SellDifferValue": 0,
      "GroupDate": "/Date(1505263794000)/"
    },
    {
      "Id": 0,
      "TypeName": "Vàng SJC 1L, 10L, 1KG",
      "BranchName": "Hồ Chí Minh",
      "Buy": "36,580",
      "BuyValue": 36580000.0,
      "Sell": "36,780",
      "SellValue": 36780000.0,
      "BuyDiffer": null,
      "BuyDifferValue": 0,
      "SellDiffer": null,
      "SellDifferValue": 0,
      "GroupDate": "/Date(1505264185000)/"
    },
    {
      "Id": 0,
      "TypeName": "Vàng SJC 1L, 10L, 1KG",
      "BranchName": "Hồ Chí Minh",
      "Buy": "36,500",
      "BuyValue": 36500000.0,
      "Sell": "36,700",
      "SellValue": 36700000.0,
      "BuyDiffer": null,
      "BuyDifferValue": 0,
      "SellDiffer": null,
      "SellDifferValue": 0,
      "GroupDate": "/Date(1505327051000)/"
    },
    {
      "Id": 0,
      "TypeName": "Vàng SJC 1L, 10L, 1KG",
      "BranchName": "Hồ Chí Minh",
      "Buy": "36,480",
      "BuyValue": 36480000.0,
      "Sell": "36,680",
      "SellValue": 36680000.0,
      "BuyDiffer": null,
      "BuyDifferValue": 0,
      "SellDiffer": null,
      "SellDifferValue": 0,
      "GroupDate": "/Date(1505328336000)/"
    },
    {
      "Id": 0,
      "TypeName": "Vàng SJC 1L, 10L, 1KG",
      "BranchName": "Hồ Chí Minh",
      "Buy": "36,470",
      "BuyValue": 36470000.0,
      "Sell": "36,670",
      "SellValue": 36670000.0,
      "BuyDiffer": null,
      "BuyDifferValue": 0,
      "SellDiffer": null,
      "SellDifferValue": 0,
      "GroupDate": "/Date(1505329635000)/"
    },
    {
      "Id": 0,
      "TypeName": "Vàng SJC 1L, 10L, 1KG",
      "BranchName": "Hồ Chí Minh",
      "Buy": "36,490",
      "BuyValue": 36490000.0,
      "Sell": "36,690",
      "SellValue": 36690000.0,
      "BuyDiffer": null,
      "BuyDifferValue": 0,
      "SellDiffer": null,
      "SellDifferValue": 0,
      "GroupDate": "/Date(1505331006000)/"
    },
    {
      "Id": 0,
      "TypeName": "Vàng SJC 1L, 10L, 1KG",
      "BranchName": "Hồ Chí Minh",
      "Buy": "36,500",
      "BuyValue": 36500000.0,
      "Sell": "36,700",
      "SellValue": 36700000.0,
      "BuyDiffer": null,
      "BuyDifferValue": 0,
      "SellDiffer": null,
      "SellDifferValue": 0,
      "GroupDate": "/Date(1505349438000)/"
    },
    {
      "Id": 0,
      "TypeName": "Vàng SJC 1L, 10L, 1KG",
      "BranchName": "Hồ Chí Minh",
      "Buy": "36,500",
      "BuyValue": 36500000.0,
      "Sell": "36,700",
      "SellValue": 36700000.0,
      "BuyDiffer": null,
      "BuyDifferValue": 0,
      "SellDiffer": null,
      "SellDifferValue": 0,
      "GroupDate": "/Date(1505349445000)/"
    },
    {
      "Id": 0,
      "TypeName": "Vàng SJC 1L, 10L, 1KG",
      "BranchName": "Hồ Chí Minh",
      "Buy": "36,570",
      "BuyValue": 36570000.0,
      "Sell": "36,770",
      "SellValue": 36770000.0,
      "BuyDiffer": null,
      "BuyDifferValue": 0,
      "SellDiffer": null,
      "SellDifferValue": 0,
      "GroupDate": "/Date(1505413191000)/"
    },
    {
      "Id": 0,
      "TypeName": "Vàng SJC 1L, 10L, 1KG",
      "BranchName": "Hồ Chí Minh",
      "Buy": "36,550",
      "BuyValue": 36550000.0,
      "Sell": "36,750",
      "SellValue": 36750000.0,
      "BuyDiffer": null,
      "BuyDifferValue": 0,
      "SellDiffer": null,
      "SellDifferValue": 0,
      "GroupDate": "/Date(1505416004000)/"
    },
    {
      "Id": 0,
      "TypeName": "Vàng SJC 1L, 10L, 1KG",
      "BranchName": "Hồ Chí Minh",
      "Buy": "36,560",
      "BuyValue": 36560000.0,
      "Sell": "36,760",
      "SellValue": 36760000.0,
      "BuyDiffer": null,
      "BuyDifferValue": 0,
      "SellDiffer": null,
      "SellDifferValue": 0,
      "GroupDate": "/Date(1505417574000)/"
    },
    {
      "Id": 0,
      "TypeName": "Vàng SJC 1L, 10L, 1KG",
      "BranchName": "Hồ Chí Minh",
      "Buy": "36,580",
      "BuyValue": 36580000.0,
      "Sell": "36,780",
      "SellValue": 36780000.0,
      "BuyDiffer": null,
      "BuyDifferValue": 0,
      "SellDiffer": null,
      "SellDifferValue": 0,
      "GroupDate": "/Date(1505418499000)/"
    },
    {
      "Id": 0,
      "TypeName": "Vàng SJC 1L, 10L, 1KG",
      "BranchName": "Hồ Chí Minh",
      "Buy": "36,560",
      "BuyValue": 36560000.0,
      "Sell": "36,760",
      "SellValue": 36760000.0,
      "BuyDiffer": null,
      "BuyDifferValue": 0,
      "SellDiffer": null,
      "SellDifferValue": 0,
      "GroupDate": "/Date(1505423168000)/"
    },
    {
      "Id": 0,
      "TypeName": "Vàng SJC 1L, 10L, 1KG",
      "BranchName": "Hồ Chí Minh",
      "Buy": "36,500",
      "BuyValue": 36500000.0,
      "Sell": "36,700",
      "SellValue": 36700000.0,
      "BuyDiffer": null,
      "BuyDifferValue": 0,
      "SellDiffer": null,
      "SellDifferValue": 0,
      "GroupDate": "/Date(1505931636000)/"
    },
    {
      "Id": 0,
      "TypeName": "Vàng SJC 1L, 10L, 1KG",
      "BranchName": "Hồ Chí Minh",
      "Buy": "36,480",
      "BuyValue": 36480000.0,
      "Sell": "36,680",
      "SellValue": 36680000.0,
      "BuyDiffer": null,
      "BuyDifferValue": 0,
      "SellDiffer": null,
      "SellDifferValue": 0,
      "GroupDate": "/Date(1505932379000)/"
    },
    {
      "Id": 0,
      "TypeName": "Vàng SJC 1L, 10L, 1KG",
      "BranchName": "Hồ Chí Minh",
      "Buy": "36,500",
      "BuyValue": 36500000.0,
      "Sell": "36,700",
      "SellValue": 36700000.0,
      "BuyDiffer": null,
      "BuyDifferValue": 0,
      "SellDiffer": null,
      "SellDifferValue": 0,
      "GroupDate": "/Date(1505934915000)/"
    },
    {
      "Id": 0,
      "TypeName": "Vàng SJC 1L, 10L, 1KG",
      "BranchName": "Hồ Chí Minh",
      "Buy": "36,470",
      "BuyValue": 36470000.0,
      "Sell": "36,670",
      "SellValue": 36670000.0,
      "BuyDiffer": null,
      "BuyDifferValue": 0,
      "SellDiffer": null,
      "SellDifferValue": 0,
      "GroupDate": "/Date(1505942768000)/"
    },
    {
      "Id": 0,
      "TypeName": "Vàng SJC 1L, 10L, 1KG",
      "BranchName": "Hồ Chí Minh",
      "Buy": "36,460",
      "BuyValue": 36460000.0,
      "Sell": "36,660",
      "SellValue": 36660000.0,
      "BuyDiffer": null,
      "BuyDifferValue": 0,
      "SellDiffer": null,
      "SellDifferValue": 0,
      "GroupDate": "/Date(1505949701000)/"
    },
    {
      "Id": 0,
      "TypeName": "Vàng SJC 1L, 10L, 1KG",
      "BranchName": "Hồ Chí Minh",
      "Buy": "36,470",
      "BuyValue": 36470000.0,
      "Sell": "36,670",
      "SellValue": 36670000.0,
      "BuyDiffer": null,
      "BuyDifferValue": 0,
      "SellDiffer": null,
      "SellDifferValue": 0,
      "GroupDate": "/Date(1505950794000)/"
    },
    {
      "Id": 0,
      "TypeName": "Vàng SJC 1L, 10L, 1KG",
      "BranchName": "Hồ Chí Minh",
      "Buy": "36,460",
      "BuyValue": 36460000.0,
      "Sell": "36,660",
      "SellValue": 36660000.0,
      "BuyDiffer": null,
      "BuyDifferValue": 0,
      "SellDiffer": null,
      "SellDifferValue": 0,
      "GroupDate": "/Date(1505951019000)/"
    },
    {
      "Id": 0,
      "TypeName": "Vàng SJC 1L, 10L, 1KG",
      "BranchName": "Hồ Chí Minh",
      "Buy": "36,450",
      "BuyValue": 36450000.0,
      "Sell": "36,650",
      "SellValue": 36650000.0,
      "BuyDiffer": null,
      "BuyDifferValue": 0,
      "SellDiffer": null,
      "SellDifferValue": 0,
      "GroupDate": "/Date(1505951689000)/"
    },
    {
      "Id": 0,
      "TypeName": "Vàng SJC 1L, 10L, 1KG",
      "BranchName": "Hồ Chí Minh",
      "Buy": "36,420",
      "BuyValue": 36420000.0,
      "Sell": "36,620",
      "SellValue": 36620000.0,
      "BuyDiffer": null,
      "BuyDifferValue": 0,
      "SellDiffer": null,
      "SellDifferValue": 0,
      "GroupDate": "/Date(1505952494000)/"
    },
    {
      "Id": 0,
      "TypeName": "Vàng SJC 1L, 10L, 1KG",
      "BranchName": "Hồ Chí Minh",
      "Buy": "36,440",
      "BuyValue": 36440000.0,
      "Sell": "36,640",
      "SellValue": 36640000.0,
      "BuyDiffer": null,
      "BuyDifferValue": 0,
      "SellDiffer": null,
      "SellDifferValue": 0,
      "GroupDate": "/Date(1505956182000)/"
    },
    {
      "Id": 0,
      "TypeName": "Vàng SJC 1L, 10L, 1KG",
      "BranchName": "Hồ Chí Minh",
      "Buy": "36,450",
      "BuyValue": 36450000.0,
      "Sell": "36,650",
      "SellValue": 36650000.0,
      "BuyDiffer": null,
      "BuyDifferValue": 0,
      "SellDiffer": null,
      "SellDifferValue": 0,
      "GroupDate": "/Date(1505959208000)/"
    },
    {
      "Id": 0,
      "TypeName": "Vàng SJC 1L, 10L, 1KG",
      "BranchName": "Hồ Chí Minh",
      "Buy": "36,460",
      "BuyValue": 36460000.0,
      "Sell": "36,660",
      "SellValue": 36660000.0,
      "BuyDiffer": null,
      "BuyDifferValue": 0,
      "SellDiffer": null,
      "SellDifferValue": 0,
      "GroupDate": "/Date(1505959271000)/"
    },
    {
      "Id": 0,
      "TypeName": "Vàng SJC 1L, 10L, 1KG",
      "BranchName": "Hồ Chí Minh",
      "Buy": "36,480",
      "BuyValue": 36480000.0,
      "Sell": "36,680",
      "SellValue": 36680000.0,
      "BuyDiffer": null,
      "BuyDifferValue": 0,
      "SellDiffer": null,
      "SellDifferValue": 0,
      "GroupDate": "/Date(1505961512000)/"
    },
    {
      "Id": 0,
      "TypeName": "Vàng SJC 1L, 10L, 1KG",
      "BranchName": "Hồ Chí Minh",
      "Buy": "36,460",
      "BuyValue": 36460000.0,
      "Sell": "36,660",
      "SellValue": 36660000.0,
      "BuyDiffer": null,
      "BuyDifferValue": 0,
      "SellDiffer": null,
      "SellDifferValue": 0,
      "GroupDate": "/Date(1506018127000)/"
    },
    {
      "Id": 0,
      "TypeName": "Vàng SJC 1L, 10L, 1KG",
      "BranchName": "Hồ Chí Minh",
      "Buy": "36,470",
      "BuyValue": 36470000.0,
      "Sell": "36,670",
      "SellValue": 36670000.0,
      "BuyDiffer": null,
      "BuyDifferValue": 0,
      "SellDiffer": null,
      "SellDifferValue": 0,
      "GroupDate": "/Date(1506018830000)/"
    },
    {
      "Id": 0,
      "TypeName": "Vàng SJC 1L, 10L, 1KG",
      "BranchName": "Hồ Chí Minh",
      "Buy": "36,500",
      "BuyValue": 36500000.0,
      "Sell": "36,700",
      "SellValue": 36700000.0,
      "BuyDiffer": null,
      "BuyDifferValue": 0,
      "SellDiffer": null,
      "SellDifferValue": 0,
      "GroupDate": "/Date(1506023836000)/"
    },
    {
      "Id": 0,
      "TypeName": "Vàng SJC 1L, 10L, 1KG",
      "BranchName": "Hồ Chí Minh",
      "Buy": "36,480",
      "BuyValue": 36480000.0,
      "Sell": "36,680",
      "SellValue": 36680000.0,
      "BuyDiffer": null,
      "BuyDifferValue": 0,
      "SellDiffer": null,
      "SellDifferValue": 0,
      "GroupDate": "/Date(1506036001000)/"
    },
    {
      "Id": 0,
      "TypeName": "Vàng SJC 1L, 10L, 1KG",
      "BranchName": "Hồ Chí Minh",
      "Buy": "36,490",
      "BuyValue": 36490000.0,
      "Sell": "36,690",
      "SellValue": 36690000.0,
      "BuyDiffer": null,
      "BuyDifferValue": 0,
      "SellDiffer": null,
      "SellDifferValue": 0,
      "GroupDate": "/Date(1506039473000)/"
    },
    {
      "Id": 0,
      "TypeName": "Vàng SJC 1L, 10L, 1KG",
      "BranchName": "Hồ Chí Minh",
      "Buy": "36,500",
      "BuyValue": 36500000.0,
      "Sell": "36,700",
      "SellValue": 36700000.0,
      "BuyDiffer": null,
      "BuyDifferValue": 0,
      "SellDiffer": null,
      "SellDifferValue": 0,
      "GroupDate": "/Date(1506039538000)/"
    },
    {
      "Id": 0,
      "TypeName": "Vàng SJC 1L, 10L, 1KG",
      "BranchName": "Hồ Chí Minh",
      "Buy": "36,500",
      "BuyValue": 36500000.0,
      "Sell": "36,700",
      "SellValue": 36700000.0,
      "BuyDiffer": null,
      "BuyDifferValue": 0,
      "SellDiffer": null,
      "SellDifferValue": 0,
      "GroupDate": "/Date(1506104423000)/"
    },
    {
      "Id": 0,
      "TypeName": "Vàng SJC 1L, 10L, 1KG",
      "BranchName": "Hồ Chí Minh",
      "Buy": "36,520",
      "BuyValue": 36520000.0,
      "Sell": "36,720",
      "SellValue": 36720000.0,
      "BuyDiffer": null,
      "BuyDifferValue": 0,
      "SellDiffer": null,
      "SellDifferValue": 0,
      "GroupDate": "/Date(1506108071000)/"
    },
    {
      "Id": 0,
      "TypeName": "Vàng SJC 1L, 10L, 1KG",
      "BranchName": "Hồ Chí Minh",
      "Buy": "36,530",
      "BuyValue": 36530000.0,
      "Sell": "36,730",
      "SellValue": 36730000.0,
      "BuyDiffer": null,
      "BuyDifferValue": 0,
      "SellDiffer": null,
      "SellDifferValue": 0,
      "GroupDate": "/Date(1506112184000)/"
    },
    {
      "Id": 0,
      "TypeName": "Vàng SJC 1L, 10L, 1KG",
      "BranchName": "Hồ Chí Minh",
      "Buy": "36,500",
      "BuyValue": 36500000.0,
      "Sell": "36,700",
      "SellValue": 36700000.0,
      "BuyDiffer": null,
      "BuyDifferValue": 0,
      "SellDiffer": null,
      "SellDifferValue": 0,
      "GroupDate": "/Date(1506277475000)/"
    },
    {
      "Id": 0,
      "TypeName": "Vàng SJC 1L, 10L, 1KG",
      "BranchName": "Hồ Chí Minh",
      "Buy": "36,520",
      "BuyValue": 36520000.0,
      "Sell": "36,720",
      "SellValue": 36720000.0,
      "BuyDiffer": null,
      "BuyDifferValue": 0,
      "SellDiffer": null,
      "SellDifferValue": 0,
      "GroupDate": "/Date(1506281777000)/"
    },
    {
      "Id": 0,
      "TypeName": "Vàng SJC 1L, 10L, 1KG",
      "BranchName": "Hồ Chí Minh",
      "Buy": "36,500",
      "BuyValue": 36500000.0,
      "Sell": "36,700",
      "SellValue": 36700000.0,
      "BuyDiffer": null,
      "BuyDifferValue": 0,
      "SellDiffer": null,
      "SellDifferValue": 0,
      "GroupDate": "/Date(1506287316000)/"
    },
    {
      "Id": 0,
      "TypeName": "Vàng SJC 1L, 10L, 1KG",
      "BranchName": "Hồ Chí Minh",
      "Buy": "36,500",
      "BuyValue": 36500000.0,
      "Sell": "36,700",
      "SellValue": 36700000.0,
      "BuyDiffer": null,
      "BuyDifferValue": 0,
      "SellDiffer": null,
      "SellDifferValue": 0,
      "GroupDate": "/Date(1506287320000)/"
    },
    {
      "Id": 0,
      "TypeName": "Vàng SJC 1L, 10L, 1KG",
      "BranchName": "Hồ Chí Minh",
      "Buy": "36,590",
      "BuyValue": 36590000.0,
      "Sell": "36,790",
      "SellValue": 36790000.0,
      "BuyDiffer": null,
      "BuyDifferValue": 0,
      "SellDiffer": null,
      "SellDifferValue": 0,
      "GroupDate": "/Date(1506363578000)/"
    },
    {
      "Id": 0,
      "TypeName": "Vàng SJC 1L, 10L, 1KG",
      "BranchName": "Hồ Chí Minh",
      "Buy": "36,570",
      "BuyValue": 36570000.0,
      "Sell": "36,770",
      "SellValue": 36770000.0,
      "BuyDiffer": null,
      "BuyDifferValue": 0,
      "SellDiffer": null,
      "SellDifferValue": 0,
      "GroupDate": "/Date(1506364940000)/"
    },
    {
      "Id": 0,
      "TypeName": "Vàng SJC 1L, 10L, 1KG",
      "BranchName": "Hồ Chí Minh",
      "Buy": "36,560",
      "BuyValue": 36560000.0,
      "Sell": "36,760",
      "SellValue": 36760000.0,
      "BuyDiffer": null,
      "BuyDifferValue": 0,
      "SellDiffer": null,
      "SellDifferValue": 0,
      "GroupDate": "/Date(1506367779000)/"
    },
    {
      "Id": 0,
      "TypeName": "Vàng SJC 1L, 10L, 1KG",
      "BranchName": "Hồ Chí Minh",
      "Buy": "36,550",
      "BuyValue": 36550000.0,
      "Sell": "36,750",
      "SellValue": 36750000.0,
      "BuyDiffer": null,
      "BuyDifferValue": 0,
      "SellDiffer": null,
      "SellDifferValue": 0,
      "GroupDate": "/Date(1506369812000)/"
    },
    {
      "Id": 0,
      "TypeName": "Vàng SJC 1L, 10L, 1KG",
      "BranchName": "Hồ Chí Minh",
      "Buy": "36,560",
      "BuyValue": 36560000.0,
      "Sell": "36,760",
      "SellValue": 36760000.0,
      "BuyDiffer": null,
      "BuyDifferValue": 0,
      "SellDiffer": null,
      "SellDifferValue": 0,
      "GroupDate": "/Date(1506381619000)/"
    },
    {
      "Id": 0,
      "TypeName": "Vàng SJC 1L, 10L, 1KG",
      "BranchName": "Hồ Chí Minh",
      "Buy": "36,550",
      "BuyValue": 36550000.0,
      "Sell": "36,750",
      "SellValue": 36750000.0,
      "BuyDiffer": null,
      "BuyDifferValue": 0,
      "SellDiffer": null,
      "SellDifferValue": 0,
      "GroupDate": "/Date(1506381951000)/"
    },
    {
      "Id": 0,
      "TypeName": "Vàng SJC 1L, 10L, 1KG",
      "BranchName": "Hồ Chí Minh",
      "Buy": "36,530",
      "BuyValue": 36530000.0,
      "Sell": "36,730",
      "SellValue": 36730000.0,
      "BuyDiffer": null,
      "BuyDifferValue": 0,
      "SellDiffer": null,
      "SellDifferValue": 0,
      "GroupDate": "/Date(1506384751000)/"
    },
    {
      "Id": 0,
      "TypeName": "Vàng SJC 1L, 10L, 1KG",
      "BranchName": "Hồ Chí Minh",
      "Buy": "36,520",
      "BuyValue": 36520000.0,
      "Sell": "36,720",
      "SellValue": 36720000.0,
      "BuyDiffer": null,
      "BuyDifferValue": 0,
      "SellDiffer": null,
      "SellDifferValue": 0,
      "GroupDate": "/Date(1506387500000)/"
    },
    {
      "Id": 0,
      "TypeName": "Vàng SJC 1L, 10L, 1KG",
      "BranchName": "Hồ Chí Minh",
      "Buy": "36,450",
      "BuyValue": 36450000.0,
      "Sell": "36,650",
      "SellValue": 36650000.0,
      "BuyDiffer": null,
      "BuyDifferValue": 0,
      "SellDiffer": null,
      "SellDifferValue": 0,
      "GroupDate": "/Date(1506449905000)/"
    },
    {
      "Id": 0,
      "TypeName": "Vàng SJC 1L, 10L, 1KG",
      "BranchName": "Hồ Chí Minh",
      "Buy": "36,470",
      "BuyValue": 36470000.0,
      "Sell": "36,670",
      "SellValue": 36670000.0,
      "BuyDiffer": null,
      "BuyDifferValue": 0,
      "SellDiffer": null,
      "SellDifferValue": 0,
      "GroupDate": "/Date(1506450853000)/"
    },
    {
      "Id": 0,
      "TypeName": "Vàng SJC 1L, 10L, 1KG",
      "BranchName": "Hồ Chí Minh",
      "Buy": "36,450",
      "BuyValue": 36450000.0,
      "Sell": "36,650",
      "SellValue": 36650000.0,
      "BuyDiffer": null,
      "BuyDifferValue": 0,
      "SellDiffer": null,
      "SellDifferValue": 0,
      "GroupDate": "/Date(1506453870000)/"
    },
    {
      "Id": 0,
      "TypeName": "Vàng SJC 1L, 10L, 1KG",
      "BranchName": "Hồ Chí Minh",
      "Buy": "36,470",
      "BuyValue": 36470000.0,
      "Sell": "36,670",
      "SellValue": 36670000.0,
      "BuyDiffer": null,
      "BuyDifferValue": 0,
      "SellDiffer": null,
      "SellDifferValue": 0,
      "GroupDate": "/Date(1506456818000)/"
    },
    {
      "Id": 0,
      "TypeName": "Vàng SJC 1L, 10L, 1KG",
      "BranchName": "Hồ Chí Minh",
      "Buy": "36,460",
      "BuyValue": 36460000.0,
      "Sell": "36,660",
      "SellValue": 36660000.0,
      "BuyDiffer": null,
      "BuyDifferValue": 0,
      "SellDiffer": null,
      "SellDifferValue": 0,
      "GroupDate": "/Date(1506469179000)/"
    },
    {
      "Id": 0,
      "TypeName": "Vàng SJC 1L, 10L, 1KG",
      "BranchName": "Hồ Chí Minh",
      "Buy": "36,450",
      "BuyValue": 36450000.0,
      "Sell": "36,650",
      "SellValue": 36650000.0,
      "BuyDiffer": null,
      "BuyDifferValue": 0,
      "SellDiffer": null,
      "SellDifferValue": 0,
      "GroupDate": "/Date(1506469864000)/"
    },
    {
      "Id": 0,
      "TypeName": "Vàng SJC 1L, 10L, 1KG",
      "BranchName": "Hồ Chí Minh",
      "Buy": "36,420",
      "BuyValue": 36420000.0,
      "Sell": "36,620",
      "SellValue": 36620000.0,
      "BuyDiffer": null,
      "BuyDifferValue": 0,
      "SellDiffer": null,
      "SellDifferValue": 0,
      "GroupDate": "/Date(1506475200000)/"
    },
    {
      "Id": 0,
      "TypeName": "Vàng SJC 1L, 10L, 1KG",
      "BranchName": "Hồ Chí Minh",
      "Buy": "36,400",
      "BuyValue": 36400000.0,
      "Sell": "36,600",
      "SellValue": 36600000.0,
      "BuyDiffer": null,
      "BuyDifferValue": 0,
      "SellDiffer": null,
      "SellDifferValue": 0,
      "GroupDate": "/Date(1506476276000)/"
    },
    {
      "Id": 0,
      "TypeName": "Vàng SJC 1L, 10L, 1KG",
      "BranchName": "Hồ Chí Minh",
      "Buy": "36,370",
      "BuyValue": 36370000.0,
      "Sell": "36,570",
      "SellValue": 36570000.0,
      "BuyDiffer": null,
      "BuyDifferValue": 0,
      "SellDiffer": null,
      "SellDifferValue": 0,
      "GroupDate": "/Date(1506536929000)/"
    },
    {
      "Id": 0,
      "TypeName": "Vàng SJC 1L, 10L, 1KG",
      "BranchName": "Hồ Chí Minh",
      "Buy": "36,350",
      "BuyValue": 36350000.0,
      "Sell": "36,550",
      "SellValue": 36550000.0,
      "BuyDiffer": null,
      "BuyDifferValue": 0,
      "SellDiffer": null,
      "SellDifferValue": 0,
      "GroupDate": "/Date(1506538450000)/"
    },
    {
      "Id": 0,
      "TypeName": "Vàng SJC 1L, 10L, 1KG",
      "BranchName": "Hồ Chí Minh",
      "Buy": "36,360",
      "BuyValue": 36360000.0,
      "Sell": "36,560",
      "SellValue": 36560000.0,
      "BuyDiffer": null,
      "BuyDifferValue": 0,
      "SellDiffer": null,
      "SellDifferValue": 0,
      "GroupDate": "/Date(1506540397000)/"
    },
    {
      "Id": 0,
      "TypeName": "Vàng SJC 1L, 10L, 1KG",
      "BranchName": "Hồ Chí Minh",
      "Buy": "36,370",
      "BuyValue": 36370000.0,
      "Sell": "36,570",
      "SellValue": 36570000.0,
      "BuyDiffer": null,
      "BuyDifferValue": 0,
      "SellDiffer": null,
      "SellDifferValue": 0,
      "GroupDate": "/Date(1506541333000)/"
    },
    {
      "Id": 0,
      "TypeName": "Vàng SJC 1L, 10L, 1KG",
      "BranchName": "Hồ Chí Minh",
      "Buy": "36,320",
      "BuyValue": 36320000.0,
      "Sell": "36,520",
      "SellValue": 36520000.0,
      "BuyDiffer": null,
      "BuyDifferValue": 0,
      "SellDiffer": null,
      "SellDifferValue": 0,
      "GroupDate": "/Date(1507142925000)/"
    },
    {
      "Id": 0,
      "TypeName": "Vàng SJC 1L, 10L, 1KG",
      "BranchName": "Hồ Chí Minh",
      "Buy": "36,330",
      "BuyValue": 36330000.0,
      "Sell": "36,530",
      "SellValue": 36530000.0,
      "BuyDiffer": null,
      "BuyDifferValue": 0,
      "SellDiffer": null,
      "SellDifferValue": 0,
      "GroupDate": "/Date(1507146642000)/"
    },
    {
      "Id": 0,
      "TypeName": "Vàng SJC 1L, 10L, 1KG",
      "BranchName": "Hồ Chí Minh",
      "Buy": "36,340",
      "BuyValue": 36340000.0,
      "Sell": "36,540",
      "SellValue": 36540000.0,
      "BuyDiffer": null,
      "BuyDifferValue": 0,
      "SellDiffer": null,
      "SellDifferValue": 0,
      "GroupDate": "/Date(1507162147000)/"
    },
    {
      "Id": 0,
      "TypeName": "Vàng SJC 1L, 10L, 1KG",
      "BranchName": "Hồ Chí Minh",
      "Buy": "36,350",
      "BuyValue": 36350000.0,
      "Sell": "36,550",
      "SellValue": 36550000.0,
      "BuyDiffer": null,
      "BuyDifferValue": 0,
      "SellDiffer": null,
      "SellDifferValue": 0,
      "GroupDate": "/Date(1507163285000)/"
    },
    {
      "Id": 0,
      "TypeName": "Vàng SJC 1L, 10L, 1KG",
      "BranchName": "Hồ Chí Minh",
      "Buy": "36,370",
      "BuyValue": 36370000.0,
      "Sell": "36,570",
      "SellValue": 36570000.0,
      "BuyDiffer": null,
      "BuyDifferValue": 0,
      "SellDiffer": null,
      "SellDifferValue": 0,
      "GroupDate": "/Date(1507164782000)/"
    },
    {
      "Id": 0,
      "TypeName": "Vàng SJC 1L, 10L, 1KG",
      "BranchName": "Hồ Chí Minh",
      "Buy": "36,380",
      "BuyValue": 36380000.0,
      "Sell": "36,580",
      "SellValue": 36580000.0,
      "BuyDiffer": null,
      "BuyDifferValue": 0,
      "SellDiffer": null,
      "SellDifferValue": 0,
      "GroupDate": "/Date(1507167441000)/"
    },
    {
      "Id": 0,
      "TypeName": "Vàng SJC 1L, 10L, 1KG",
      "BranchName": "Hồ Chí Minh",
      "Buy": "36,390",
      "BuyValue": 36390000.0,
      "Sell": "36,590",
      "SellValue": 36590000.0,
      "BuyDiffer": null,
      "BuyDifferValue": 0,
      "SellDiffer": null,
      "SellDifferValue": 0,
      "GroupDate": "/Date(1507168358000)/"
    },
    {
      "Id": 0,
      "TypeName": "Vàng SJC 1L, 10L, 1KG",
      "BranchName": "Hồ Chí Minh",
      "Buy": "36,400",
      "BuyValue": 36400000.0,
      "Sell": "36,600",
      "SellValue": 36600000.0,
      "BuyDiffer": null,
      "BuyDifferValue": 0,
      "SellDiffer": null,
      "SellDifferValue": 0,
      "GroupDate": "/Date(1507169958000)/"
    },
    {
      "Id": 0,
      "TypeName": "Vàng SJC 1L, 10L, 1KG",
      "BranchName": "Hồ Chí Minh",
      "Buy": "36,340",
      "BuyValue": 36340000.0,
      "Sell": "36,540",
      "SellValue": 36540000.0,
      "BuyDiffer": null,
      "BuyDifferValue": 0,
      "SellDiffer": null,
      "SellDifferValue": 0,
      "GroupDate": "/Date(1507227882000)/"
    },
    {
      "Id": 0,
      "TypeName": "Vàng SJC 1L, 10L, 1KG",
      "BranchName": "Hồ Chí Minh",
      "Buy": "36,350",
      "BuyValue": 36350000.0,
      "Sell": "36,550",
      "SellValue": 36550000.0,
      "BuyDiffer": null,
      "BuyDifferValue": 0,
      "SellDiffer": null,
      "SellDifferValue": 0,
      "GroupDate": "/Date(1507252455000)/"
    },
    {
      "Id": 0,
      "TypeName": "Vàng SJC 1L, 10L, 1KG",
      "BranchName": "Hồ Chí Minh",
      "Buy": "36,370",
      "BuyValue": 36370000.0,
      "Sell": "36,570",
      "SellValue": 36570000.0,
      "BuyDiffer": null,
      "BuyDifferValue": 0,
      "SellDiffer": null,
      "SellDifferValue": 0,
      "GroupDate": "/Date(1507253442000)/"
    },
    {
      "Id": 0,
      "TypeName": "Vàng SJC 1L, 10L, 1KG",
      "BranchName": "Hồ Chí Minh",
      "Buy": "36,430",
      "BuyValue": 36430000.0,
      "Sell": "36,630",
      "SellValue": 36630000.0,
      "BuyDiffer": null,
      "BuyDifferValue": 0,
      "SellDiffer": null,
      "SellDifferValue": 0,
      "GroupDate": "/Date(1507314806000)/"
    },
    {
      "Id": 0,
      "TypeName": "Vàng SJC 1L, 10L, 1KG",
      "BranchName": "Hồ Chí Minh",
      "Buy": "36,410",
      "BuyValue": 36410000.0,
      "Sell": "36,610",
      "SellValue": 36610000.0,
      "BuyDiffer": null,
      "BuyDifferValue": 0,
      "SellDiffer": null,
      "SellDifferValue": 0,
      "GroupDate": "/Date(1507315744000)/"
    },
    {
      "Id": 0,
      "TypeName": "Vàng SJC 1L, 10L, 1KG",
      "BranchName": "Hồ Chí Minh",
      "Buy": "36,430",
      "BuyValue": 36430000.0,
      "Sell": "36,630",
      "SellValue": 36630000.0,
      "BuyDiffer": null,
      "BuyDifferValue": 0,
      "SellDiffer": null,
      "SellDifferValue": 0,
      "GroupDate": "/Date(1507486562000)/"
    },
    {
      "Id": 0,
      "TypeName": "Vàng SJC 1L, 10L, 1KG",
      "BranchName": "Hồ Chí Minh",
      "Buy": "36,410",
      "BuyValue": 36410000.0,
      "Sell": "36,610",
      "SellValue": 36610000.0,
      "BuyDiffer": null,
      "BuyDifferValue": 0,
      "SellDiffer": null,
      "SellDifferValue": 0,
      "GroupDate": "/Date(1507489228000)/"
    },
    {
      "Id": 0,
      "TypeName": "Vàng SJC 1L, 10L, 1KG",
      "BranchName": "Hồ Chí Minh",
      "Buy": "36,430",
      "BuyValue": 36430000.0,
      "Sell": "36,630",
      "SellValue": 36630000.0,
      "BuyDiffer": null,
      "BuyDifferValue": 0,
      "SellDiffer": null,
      "SellDifferValue": 0,
      "GroupDate": "/Date(1507490288000)/"
    },
    {
      "Id": 0,
      "TypeName": "Vàng SJC 1L, 10L, 1KG",
      "BranchName": "Hồ Chí Minh",
      "Buy": "36,420",
      "BuyValue": 36420000.0,
      "Sell": "36,620",
      "SellValue": 36620000.0,
      "BuyDiffer": null,
      "BuyDifferValue": 0,
      "SellDiffer": null,
      "SellDifferValue": 0,
      "GroupDate": "/Date(1507492585000)/"
    },
    {
      "Id": 0,
      "TypeName": "Vàng SJC 1L, 10L, 1KG",
      "BranchName": "Hồ Chí Minh",
      "Buy": "36,430",
      "BuyValue": 36430000.0,
      "Sell": "36,630",
      "SellValue": 36630000.0,
      "BuyDiffer": null,
      "BuyDifferValue": 0,
      "SellDiffer": null,
      "SellDifferValue": 0,
      "GroupDate": "/Date(1507494397000)/"
    },
    {
      "Id": 0,
      "TypeName": "Vàng SJC 1L, 10L, 1KG",
      "BranchName": "Hồ Chí Minh",
      "Buy": "36,420",
      "BuyValue": 36420000.0,
      "Sell": "36,620",
      "SellValue": 36620000.0,
      "BuyDiffer": null,
      "BuyDifferValue": 0,
      "SellDiffer": null,
      "SellDifferValue": 0,
      "GroupDate": "/Date(1507506260000)/"
    },
    {
      "Id": 0,
      "TypeName": "Vàng SJC 1L, 10L, 1KG",
      "BranchName": "Hồ Chí Minh",
      "Buy": "36,410",
      "BuyValue": 36410000.0,
      "Sell": "36,610",
      "SellValue": 36610000.0,
      "BuyDiffer": null,
      "BuyDifferValue": 0,
      "SellDiffer": null,
      "SellDifferValue": 0,
      "GroupDate": "/Date(1507507962000)/"
    },
    {
      "Id": 0,
      "TypeName": "Vàng SJC 1L, 10L, 1KG",
      "BranchName": "Hồ Chí Minh",
      "Buy": "36,400",
      "BuyValue": 36400000.0,
      "Sell": "36,600",
      "SellValue": 36600000.0,
      "BuyDiffer": null,
      "BuyDifferValue": 0,
      "SellDiffer": null,
      "SellDifferValue": 0,
      "GroupDate": "/Date(1507508361000)/"
    },
    {
      "Id": 0,
      "TypeName": "Vàng SJC 1L, 10L, 1KG",
      "BranchName": "Hồ Chí Minh",
      "Buy": "36,410",
      "BuyValue": 36410000.0,
      "Sell": "36,610",
      "SellValue": 36610000.0,
      "BuyDiffer": null,
      "BuyDifferValue": 0,
      "SellDiffer": null,
      "SellDifferValue": 0,
      "GroupDate": "/Date(1507514277000)/"
    },
    {
      "Id": 0,
      "TypeName": "Vàng SJC 1L, 10L, 1KG",
      "BranchName": "Hồ Chí Minh",
      "Buy": "36,450",
      "BuyValue": 36450000.0,
      "Sell": "36,650",
      "SellValue": 36650000.0,
      "BuyDiffer": null,
      "BuyDifferValue": 0,
      "SellDiffer": null,
      "SellDifferValue": 0,
      "GroupDate": "/Date(1507573159000)/"
    },
    {
      "Id": 0,
      "TypeName": "Vàng SJC 1L, 10L, 1KG",
      "BranchName": "Hồ Chí Minh",
      "Buy": "36,440",
      "BuyValue": 36440000.0,
      "Sell": "36,640",
      "SellValue": 36640000.0,
      "BuyDiffer": null,
      "BuyDifferValue": 0,
      "SellDiffer": null,
      "SellDifferValue": 0,
      "GroupDate": "/Date(1507575989000)/"
    },
    {
      "Id": 0,
      "TypeName": "Vàng SJC 1L, 10L, 1KG",
      "BranchName": "Hồ Chí Minh",
      "Buy": "36,430",
      "BuyValue": 36430000.0,
      "Sell": "36,630",
      "SellValue": 36630000.0,
      "BuyDiffer": null,
      "BuyDifferValue": 0,
      "SellDiffer": null,
      "SellDifferValue": 0,
      "GroupDate": "/Date(1507577178000)/"
    },
    {
      "Id": 0,
      "TypeName": "Vàng SJC 1L, 10L, 1KG",
      "BranchName": "Hồ Chí Minh",
      "Buy": "36,440",
      "BuyValue": 36440000.0,
      "Sell": "36,640",
      "SellValue": 36640000.0,
      "BuyDiffer": null,
      "BuyDifferValue": 0,
      "SellDiffer": null,
      "SellDifferValue": 0,
      "GroupDate": "/Date(1507600645000)/"
    },
    {
      "Id": 0,
      "TypeName": "Vàng SJC 1L, 10L, 1KG",
      "BranchName": "Hồ Chí Minh",
      "Buy": "36,460",
      "BuyValue": 36460000.0,
      "Sell": "36,660",
      "SellValue": 36660000.0,
      "BuyDiffer": null,
      "BuyDifferValue": 0,
      "SellDiffer": null,
      "SellDifferValue": 0,
      "GroupDate": "/Date(1507659944000)/"
    },
    {
      "Id": 0,
      "TypeName": "Vàng SJC 1L, 10L, 1KG",
      "BranchName": "Hồ Chí Minh",
      "Buy": "36,450",
      "BuyValue": 36450000.0,
      "Sell": "36,650",
      "SellValue": 36650000.0,
      "BuyDiffer": null,
      "BuyDifferValue": 0,
      "SellDiffer": null,
      "SellDifferValue": 0,
      "GroupDate": "/Date(1507660487000)/"
    },
    {
      "Id": 0,
      "TypeName": "Vàng SJC 1L, 10L, 1KG",
      "BranchName": "Hồ Chí Minh",
      "Buy": "36,430",
      "BuyValue": 36430000.0,
      "Sell": "36,630",
      "SellValue": 36630000.0,
      "BuyDiffer": null,
      "BuyDifferValue": 0,
      "SellDiffer": null,
      "SellDifferValue": 0,
      "GroupDate": "/Date(1507680118000)/"
    },
    {
      "Id": 0,
      "TypeName": "Vàng SJC 1L, 10L, 1KG",
      "BranchName": "Hồ Chí Minh",
      "Buy": "36,460",
      "BuyValue": 36460000.0,
      "Sell": "36,660",
      "SellValue": 36660000.0,
      "BuyDiffer": null,
      "BuyDifferValue": 0,
      "SellDiffer": null,
      "SellDifferValue": 0,
      "GroupDate": "/Date(1507746176000)/"
    },
    {
      "Id": 0,
      "TypeName": "Vàng SJC 1L, 10L, 1KG",
      "BranchName": "Hồ Chí Minh",
      "Buy": "36,470",
      "BuyValue": 36470000.0,
      "Sell": "36,670",
      "SellValue": 36670000.0,
      "BuyDiffer": null,
      "BuyDifferValue": 0,
      "SellDiffer": null,
      "SellDifferValue": 0,
      "GroupDate": "/Date(1507753581000)/"
    },
    {
      "Id": 0,
      "TypeName": "Vàng SJC 1L, 10L, 1KG",
      "BranchName": "Hồ Chí Minh",
      "Buy": "36,480",
      "BuyValue": 36480000.0,
      "Sell": "36,680",
      "SellValue": 36680000.0,
      "BuyDiffer": null,
      "BuyDifferValue": 0,
      "SellDiffer": null,
      "SellDifferValue": 0,
      "GroupDate": "/Date(1507768136000)/"
    },
    {
      "Id": 0,
      "TypeName": "Vàng SJC 1L, 10L, 1KG",
      "BranchName": "Hồ Chí Minh",
      "Buy": "36,490",
      "BuyValue": 36490000.0,
      "Sell": "36,690",
      "SellValue": 36690000.0,
      "BuyDiffer": null,
      "BuyDifferValue": 0,
      "SellDiffer": null,
      "SellDifferValue": 0,
      "GroupDate": "/Date(1507769035000)/"
    },
    {
      "Id": 0,
      "TypeName": "Vàng SJC 1L, 10L, 1KG",
      "BranchName": "Hồ Chí Minh",
      "Buy": "36,480",
      "BuyValue": 36480000.0,
      "Sell": "36,680",
      "SellValue": 36680000.0,
      "BuyDiffer": null,
      "BuyDifferValue": 0,
      "SellDiffer": null,
      "SellDifferValue": 0,
      "GroupDate": "/Date(1507832426000)/"
    },
    {
      "Id": 0,
      "TypeName": "Vàng SJC 1L, 10L, 1KG",
      "BranchName": "Hồ Chí Minh",
      "Buy": "36,490",
      "BuyValue": 36490000.0,
      "Sell": "36,690",
      "SellValue": 36690000.0,
      "BuyDiffer": null,
      "BuyDifferValue": 0,
      "SellDiffer": null,
      "SellDifferValue": 0,
      "GroupDate": "/Date(1507837678000)/"
    },
    {
      "Id": 0,
      "TypeName": "Vàng SJC 1L, 10L, 1KG",
      "BranchName": "Hồ Chí Minh",
      "Buy": "36,480",
      "BuyValue": 36480000.0,
      "Sell": "36,680",
      "SellValue": 36680000.0,
      "BuyDiffer": null,
      "BuyDifferValue": 0,
      "SellDiffer": null,
      "SellDifferValue": 0,
      "GroupDate": "/Date(1507841629000)/"
    },
    {
      "Id": 0,
      "TypeName": "Vàng SJC 1L, 10L, 1KG",
      "BranchName": "Hồ Chí Minh",
      "Buy": "36,480",
      "BuyValue": 36480000.0,
      "Sell": "36,680",
      "SellValue": 36680000.0,
      "BuyDiffer": null,
      "BuyDifferValue": 0,
      "SellDiffer": null,
      "SellDifferValue": 0,
      "GroupDate": "/Date(1507843696000)/"
    },
    {
      "Id": 0,
      "TypeName": "Vàng SJC 1L, 10L, 1KG",
      "BranchName": "Hồ Chí Minh",
      "Buy": "36,460",
      "BuyValue": 36460000.0,
      "Sell": "36,660",
      "SellValue": 36660000.0,
      "BuyDiffer": null,
      "BuyDifferValue": 0,
      "SellDiffer": null,
      "SellDifferValue": 0,
      "GroupDate": "/Date(1507861452000)/"
    },
    {
      "Id": 0,
      "TypeName": "Vàng SJC 1L, 10L, 1KG",
      "BranchName": "Hồ Chí Minh",
      "Buy": "36,560",
      "BuyValue": 36560000.0,
      "Sell": "36,760",
      "SellValue": 36760000.0,
      "BuyDiffer": null,
      "BuyDifferValue": 0,
      "SellDiffer": null,
      "SellDifferValue": 0,
      "GroupDate": "/Date(1507919112000)/"
    },
    {
      "Id": 0,
      "TypeName": "Vàng SJC 1L, 10L, 1KG",
      "BranchName": "Hồ Chí Minh",
      "Buy": "36,540",
      "BuyValue": 36540000.0,
      "Sell": "36,740",
      "SellValue": 36740000.0,
      "BuyDiffer": null,
      "BuyDifferValue": 0,
      "SellDiffer": null,
      "SellDifferValue": 0,
      "GroupDate": "/Date(1507922937000)/"
    },
    {
      "Id": 0,
      "TypeName": "Vàng SJC 1L, 10L, 1KG",
      "BranchName": "Hồ Chí Minh",
      "Buy": "36,530",
      "BuyValue": 36530000.0,
      "Sell": "36,730",
      "SellValue": 36730000.0,
      "BuyDiffer": null,
      "BuyDifferValue": 0,
      "SellDiffer": null,
      "SellDifferValue": 0,
      "GroupDate": "/Date(1507927915000)/"
    },
    {
      "Id": 0,
      "TypeName": "Vàng SJC 1L, 10L, 1KG",
      "BranchName": "Hồ Chí Minh",
      "Buy": "36,490",
      "BuyValue": 36490000.0,
      "Sell": "36,690",
      "SellValue": 36690000.0,
      "BuyDiffer": null,
      "BuyDifferValue": 0,
      "SellDiffer": null,
      "SellDifferValue": 0,
      "GroupDate": "/Date(1508091816000)/"
    },
    {
      "Id": 0,
      "TypeName": "Vàng SJC 1L, 10L, 1KG",
      "BranchName": "Hồ Chí Minh",
      "Buy": "36,470",
      "BuyValue": 36470000.0,
      "Sell": "36,670",
      "SellValue": 36670000.0,
      "BuyDiffer": null,
      "BuyDifferValue": 0,
      "SellDiffer": null,
      "SellDifferValue": 0,
      "GroupDate": "/Date(1508096256000)/"
    },
    {
      "Id": 0,
      "TypeName": "Vàng SJC 1L, 10L, 1KG",
      "BranchName": "Hồ Chí Minh",
      "Buy": "36,480",
      "BuyValue": 36480000.0,
      "Sell": "36,680",
      "SellValue": 36680000.0,
      "BuyDiffer": null,
      "BuyDifferValue": 0,
      "SellDiffer": null,
      "SellDifferValue": 0,
      "GroupDate": "/Date(1508110832000)/"
    },
    {
      "Id": 0,
      "TypeName": "Vàng SJC 1L, 10L, 1KG",
      "BranchName": "Hồ Chí Minh",
      "Buy": "36,490",
      "BuyValue": 36490000.0,
      "Sell": "36,690",
      "SellValue": 36690000.0,
      "BuyDiffer": null,
      "BuyDifferValue": 0,
      "SellDiffer": null,
      "SellDifferValue": 0,
      "GroupDate": "/Date(1508112599000)/"
    },
    {
      "Id": 0,
      "TypeName": "Vàng SJC 1L, 10L, 1KG",
      "BranchName": "Hồ Chí Minh",
      "Buy": "36,500",
      "BuyValue": 36500000.0,
      "Sell": "36,700",
      "SellValue": 36700000.0,
      "BuyDiffer": null,
      "BuyDifferValue": 0,
      "SellDiffer": null,
      "SellDifferValue": 0,
      "GroupDate": "/Date(1508113855000)/"
    },
    {
      "Id": 0,
      "TypeName": "Vàng SJC 1L, 10L, 1KG",
      "BranchName": "Hồ Chí Minh",
      "Buy": "36,280",
      "BuyValue": 36280000.0,
      "Sell": "36,480",
      "SellValue": 36480000.0,
      "BuyDiffer": null,
      "BuyDifferValue": 0,
      "SellDiffer": null,
      "SellDifferValue": 0,
      "GroupDate": "/Date(1508869835000)/"
    },
    {
      "Id": 0,
      "TypeName": "Vàng SJC 1L, 10L, 1KG",
      "BranchName": "Hồ Chí Minh",
      "Buy": "36,270",
      "BuyValue": 36270000.0,
      "Sell": "36,470",
      "SellValue": 36470000.0,
      "BuyDiffer": null,
      "BuyDifferValue": 0,
      "SellDiffer": null,
      "SellDifferValue": 0,
      "GroupDate": "/Date(1508872080000)/"
    },
    {
      "Id": 0,
      "TypeName": "Vàng SJC 1L, 10L, 1KG",
      "BranchName": "Hồ Chí Minh",
      "Buy": "36,280",
      "BuyValue": 36280000.0,
      "Sell": "36,480",
      "SellValue": 36480000.0,
      "BuyDiffer": null,
      "BuyDifferValue": 0,
      "SellDiffer": null,
      "SellDifferValue": 0,
      "GroupDate": "/Date(1508888027000)/"
    },
    {
      "Id": 0,
      "TypeName": "Vàng SJC 1L, 10L, 1KG",
      "BranchName": "Hồ Chí Minh",
      "Buy": "36,270",
      "BuyValue": 36270000.0,
      "Sell": "36,470",
      "SellValue": 36470000.0,
      "BuyDiffer": null,
      "BuyDifferValue": 0,
      "SellDiffer": null,
      "SellDifferValue": 0,
      "GroupDate": "/Date(1508898563000)/"
    },
    {
      "Id": 0,
      "TypeName": "Vàng SJC 1L, 10L, 1KG",
      "BranchName": "Hồ Chí Minh",
      "Buy": "36,330",
      "BuyValue": 36330000.0,
      "Sell": "36,530",
      "SellValue": 36530000.0,
      "BuyDiffer": null,
      "BuyDifferValue": 0,
      "SellDiffer": null,
      "SellDifferValue": 0,
      "GroupDate": "/Date(1508955726000)/"
    },
    {
      "Id": 0,
      "TypeName": "Vàng SJC 1L, 10L, 1KG",
      "BranchName": "Hồ Chí Minh",
      "Buy": "36,310",
      "BuyValue": 36310000.0,
      "Sell": "36,510",
      "SellValue": 36510000.0,
      "BuyDiffer": null,
      "BuyDifferValue": 0,
      "SellDiffer": null,
      "SellDifferValue": 0,
      "GroupDate": "/Date(1508959430000)/"
    },
    {
      "Id": 0,
      "TypeName": "Vàng SJC 1L, 10L, 1KG",
      "BranchName": "Hồ Chí Minh",
      "Buy": "36,300",
      "BuyValue": 36300000.0,
      "Sell": "36,500",
      "SellValue": 36500000.0,
      "BuyDiffer": null,
      "BuyDifferValue": 0,
      "SellDiffer": null,
      "SellDifferValue": 0,
      "GroupDate": "/Date(1508961564000)/"
    },
    {
      "Id": 0,
      "TypeName": "Vàng SJC 1L, 10L, 1KG",
      "BranchName": "Hồ Chí Minh",
      "Buy": "36,280",
      "BuyValue": 36280000.0,
      "Sell": "36,480",
      "SellValue": 36480000.0,
      "BuyDiffer": null,
      "BuyDifferValue": 0,
      "SellDiffer": null,
      "SellDifferValue": 0,
      "GroupDate": "/Date(1508976643000)/"
    },
    {
      "Id": 0,
      "TypeName": "Vàng SJC 1L, 10L, 1KG",
      "BranchName": "Hồ Chí Minh",
      "Buy": "36,300",
      "BuyValue": 36300000.0,
      "Sell": "36,500",
      "SellValue": 36500000.0,
      "BuyDiffer": null,
      "BuyDifferValue": 0,
      "SellDiffer": null,
      "SellDifferValue": 0,
      "GroupDate": "/Date(1508976662000)/"
    },
    {
      "Id": 0,
      "TypeName": "Vàng SJC 1L, 10L, 1KG",
      "BranchName": "Hồ Chí Minh",
      "Buy": "36,270",
      "BuyValue": 36270000.0,
      "Sell": "36,470",
      "SellValue": 36470000.0,
      "BuyDiffer": null,
      "BuyDifferValue": 0,
      "SellDiffer": null,
      "SellDifferValue": 0,
      "GroupDate": "/Date(1508978087000)/"
    },
    {
      "Id": 0,
      "TypeName": "Vàng SJC 1L, 10L, 1KG",
      "BranchName": "Hồ Chí Minh",
      "Buy": "36,220",
      "BuyValue": 36220000.0,
      "Sell": "36,420",
      "SellValue": 36420000.0,
      "BuyDiffer": null,
      "BuyDifferValue": 0,
      "SellDiffer": null,
      "SellDifferValue": 0,
      "GroupDate": "/Date(1509042048000)/"
    },
    {
      "Id": 0,
      "TypeName": "Vàng SJC 1L, 10L, 1KG",
      "BranchName": "Hồ Chí Minh",
      "Buy": "36,230",
      "BuyValue": 36230000.0,
      "Sell": "36,430",
      "SellValue": 36430000.0,
      "BuyDiffer": null,
      "BuyDifferValue": 0,
      "SellDiffer": null,
      "SellDifferValue": 0,
      "GroupDate": "/Date(1509046229000)/"
    },
    {
      "Id": 0,
      "TypeName": "Vàng SJC 1L, 10L, 1KG",
      "BranchName": "Hồ Chí Minh",
      "Buy": "36,240",
      "BuyValue": 36240000.0,
      "Sell": "36,440",
      "SellValue": 36440000.0,
      "BuyDiffer": null,
      "BuyDifferValue": 0,
      "SellDiffer": null,
      "SellDifferValue": 0,
      "GroupDate": "/Date(1509049163000)/"
    },
    {
      "Id": 0,
      "TypeName": "Vàng SJC 1L, 10L, 1KG",
      "BranchName": "Hồ Chí Minh",
      "Buy": "36,250",
      "BuyValue": 36250000.0,
      "Sell": "36,450",
      "SellValue": 36450000.0,
      "BuyDiffer": null,
      "BuyDifferValue": 0,
      "SellDiffer": null,
      "SellDifferValue": 0,
      "GroupDate": "/Date(1509049352000)/"
    },
    {
      "Id": 0,
      "TypeName": "Vàng SJC 1L, 10L, 1KG",
      "BranchName": "Hồ Chí Minh",
      "Buy": "36,270",
      "BuyValue": 36270000.0,
      "Sell": "36,470",
      "SellValue": 36470000.0,
      "BuyDiffer": null,
      "BuyDifferValue": 0,
      "SellDiffer": null,
      "SellDifferValue": 0,
      "GroupDate": "/Date(1509050528000)/"
    },
    {
      "Id": 0,
      "TypeName": "Vàng SJC 1L, 10L, 1KG",
      "BranchName": "Hồ Chí Minh",
      "Buy": "36,290",
      "BuyValue": 36290000.0,
      "Sell": "36,490",
      "SellValue": 36490000.0,
      "BuyDiffer": null,
      "BuyDifferValue": 0,
      "SellDiffer": null,
      "SellDifferValue": 0,
      "GroupDate": "/Date(1509071007000)/"
    },
    {
      "Id": 0,
      "TypeName": "Vàng SJC 1L, 10L, 1KG",
      "BranchName": "Hồ Chí Minh",
      "Buy": "36,350",
      "BuyValue": 36350000.0,
      "Sell": "36,550",
      "SellValue": 36550000.0,
      "BuyDiffer": null,
      "BuyDifferValue": 0,
      "SellDiffer": null,
      "SellDifferValue": 0,
      "GroupDate": "/Date(1509127918000)/"
    },
    {
      "Id": 0,
      "TypeName": "Vàng SJC 1L, 10L, 1KG",
      "BranchName": "Hồ Chí Minh",
      "Buy": "36,340",
      "BuyValue": 36340000.0,
      "Sell": "36,540",
      "SellValue": 36540000.0,
      "BuyDiffer": null,
      "BuyDifferValue": 0,
      "SellDiffer": null,
      "SellDifferValue": 0,
      "GroupDate": "/Date(1509127968000)/"
    },
    {
      "Id": 0,
      "TypeName": "Vàng SJC 1L, 10L, 1KG",
      "BranchName": "Hồ Chí Minh",
      "Buy": "36,320",
      "BuyValue": 36320000.0,
      "Sell": "36,520",
      "SellValue": 36520000.0,
      "BuyDiffer": null,
      "BuyDifferValue": 0,
      "SellDiffer": null,
      "SellDifferValue": 0,
      "GroupDate": "/Date(1509301160000)/"
    },
    {
      "Id": 0,
      "TypeName": "Vàng SJC 1L, 10L, 1KG",
      "BranchName": "Hồ Chí Minh",
      "Buy": "36,300",
      "BuyValue": 36300000.0,
      "Sell": "36,500",
      "SellValue": 36500000.0,
      "BuyDiffer": null,
      "BuyDifferValue": 0,
      "SellDiffer": null,
      "SellDifferValue": 0,
      "GroupDate": "/Date(1509305402000)/"
    },
    {
      "Id": 0,
      "TypeName": "Vàng SJC 1L, 10L, 1KG",
      "BranchName": "Hồ Chí Minh",
      "Buy": "36,320",
      "BuyValue": 36320000.0,
      "Sell": "36,520",
      "SellValue": 36520000.0,
      "BuyDiffer": null,
      "BuyDifferValue": 0,
      "SellDiffer": null,
      "SellDifferValue": 0,
      "GroupDate": "/Date(1509312062000)/"
    },
    {
      "Id": 0,
      "TypeName": "Vàng SJC 1L, 10L, 1KG",
      "BranchName": "Hồ Chí Minh",
      "Buy": "36,310",
      "BuyValue": 36310000.0,
      "Sell": "36,510",
      "SellValue": 36510000.0,
      "BuyDiffer": null,
      "BuyDifferValue": 0,
      "SellDiffer": null,
      "SellDifferValue": 0,
      "GroupDate": "/Date(1509321343000)/"
    },
    {
      "Id": 0,
      "TypeName": "Vàng SJC 1L, 10L, 1KG",
      "BranchName": "Hồ Chí Minh",
      "Buy": "36,300",
      "BuyValue": 36300000.0,
      "Sell": "36,500",
      "SellValue": 36500000.0,
      "BuyDiffer": null,
      "BuyDifferValue": 0,
      "SellDiffer": null,
      "SellDifferValue": 0,
      "GroupDate": "/Date(1509324868000)/"
    },
    {
      "Id": 0,
      "TypeName": "Vàng SJC 1L, 10L, 1KG",
      "BranchName": "Hồ Chí Minh",
      "Buy": "36,330",
      "BuyValue": 36330000.0,
      "Sell": "36,530",
      "SellValue": 36530000.0,
      "BuyDiffer": null,
      "BuyDifferValue": 0,
      "SellDiffer": null,
      "SellDifferValue": 0,
      "GroupDate": "/Date(1509387460000)/"
    },
    {
      "Id": 0,
      "TypeName": "Vàng SJC 1L, 10L, 1KG",
      "BranchName": "Hồ Chí Minh",
      "Buy": "36,350",
      "BuyValue": 36350000.0,
      "Sell": "36,550",
      "SellValue": 36550000.0,
      "BuyDiffer": null,
      "BuyDifferValue": 0,
      "SellDiffer": null,
      "SellDifferValue": 0,
      "GroupDate": "/Date(1509391943000)/"
    },
    {
      "Id": 0,
      "TypeName": "Vàng SJC 1L, 10L, 1KG",
      "BranchName": "Hồ Chí Minh",
      "Buy": "36,360",
      "BuyValue": 36360000.0,
      "Sell": "36,560",
      "SellValue": 36560000.0,
      "BuyDiffer": null,
      "BuyDifferValue": 0,
      "SellDiffer": null,
      "SellDifferValue": 0,
      "GroupDate": "/Date(1509407649000)/"
    },
    {
      "Id": 0,
      "TypeName": "Vàng SJC 1L, 10L, 1KG",
      "BranchName": "Hồ Chí Minh",
      "Buy": "36,380",
      "BuyValue": 36380000.0,
      "Sell": "36,580",
      "SellValue": 36580000.0,
      "BuyDiffer": null,
      "BuyDifferValue": 0,
      "SellDiffer": null,
      "SellDifferValue": 0,
      "GroupDate": "/Date(1509407857000)/"
    },
    {
      "Id": 0,
      "TypeName": "Vàng SJC 1L, 10L, 1KG",
      "BranchName": "Hồ Chí Minh",
      "Buy": "36,340",
      "BuyValue": 36340000.0,
      "Sell": "36,540",
      "SellValue": 36540000.0,
      "BuyDiffer": null,
      "BuyDifferValue": 0,
      "SellDiffer": null,
      "SellDifferValue": 0,
      "GroupDate": "/Date(1509473870000)/"
    },
    {
      "Id": 0,
      "TypeName": "Vàng SJC 1L, 10L, 1KG",
      "BranchName": "Hồ Chí Minh",
      "Buy": "36,350",
      "BuyValue": 36350000.0,
      "Sell": "36,550",
      "SellValue": 36550000.0,
      "BuyDiffer": null,
      "BuyDifferValue": 0,
      "SellDiffer": null,
      "SellDifferValue": 0,
      "GroupDate": "/Date(1509476635000)/"
    },
    {
      "Id": 0,
      "TypeName": "Vàng SJC 1L, 10L, 1KG",
      "BranchName": "Hồ Chí Minh",
      "Buy": "36,370",
      "BuyValue": 36370000.0,
      "Sell": "36,570",
      "SellValue": 36570000.0,
      "BuyDiffer": null,
      "BuyDifferValue": 0,
      "SellDiffer": null,
      "SellDifferValue": 0,
      "GroupDate": "/Date(1509484642000)/"
    },
    {
      "Id": 0,
      "TypeName": "Vàng SJC 1L, 10L, 1KG",
      "BranchName": "Hồ Chí Minh",
      "Buy": "36,390",
      "BuyValue": 36390000.0,
      "Sell": "36,590",
      "SellValue": 36590000.0,
      "BuyDiffer": null,
      "BuyDifferValue": 0,
      "SellDiffer": null,
      "SellDifferValue": 0,
      "GroupDate": "/Date(1509491923000)/"
    },
    {
      "Id": 0,
      "TypeName": "Vàng SJC 1L, 10L, 1KG",
      "BranchName": "Hồ Chí Minh",
      "Buy": "36,400",
      "BuyValue": 36400000.0,
      "Sell": "36,600",
      "SellValue": 36600000.0,
      "BuyDiffer": null,
      "BuyDifferValue": 0,
      "SellDiffer": null,
      "SellDifferValue": 0,
      "GroupDate": "/Date(1509494143000)/"
    },
    {
      "Id": 0,
      "TypeName": "Vàng SJC 1L, 10L, 1KG",
      "BranchName": "Hồ Chí Minh",
      "Buy": "36,420",
      "BuyValue": 36420000.0,
      "Sell": "36,620",
      "SellValue": 36620000.0,
      "BuyDiffer": null,
      "BuyDifferValue": 0,
      "SellDiffer": null,
      "SellDifferValue": 0,
      "GroupDate": "/Date(1509496135000)/"
    },
    {
      "Id": 0,
      "TypeName": "Vàng SJC 1L, 10L, 1KG",
      "BranchName": "Hồ Chí Minh",
      "Buy": "36,450",
      "BuyValue": 36450000.0,
      "Sell": "36,650",
      "SellValue": 36650000.0,
      "BuyDiffer": null,
      "BuyDifferValue": 0,
      "SellDiffer": null,
      "SellDifferValue": 0,
      "GroupDate": "/Date(1509560419000)/"
    },
    {
      "Id": 0,
      "TypeName": "Vàng SJC 1L, 10L, 1KG",
      "BranchName": "Hồ Chí Minh",
      "Buy": "36,430",
      "BuyValue": 36430000.0,
      "Sell": "36,630",
      "SellValue": 36630000.0,
      "BuyDiffer": null,
      "BuyDifferValue": 0,
      "SellDiffer": null,
      "SellDifferValue": 0,
      "GroupDate": "/Date(1509567736000)/"
    },
    {
      "Id": 0,
      "TypeName": "Vàng SJC 1L, 10L, 1KG",
      "BranchName": "Hồ Chí Minh",
      "Buy": "36,420",
      "BuyValue": 36420000.0,
      "Sell": "36,620",
      "SellValue": 36620000.0,
      "BuyDiffer": null,
      "BuyDifferValue": 0,
      "SellDiffer": null,
      "SellDifferValue": 0,
      "GroupDate": "/Date(1509584990000)/"
    }
  ]
}