{
  "requirement_id": "REQ-022",
  "text": "Revenue/NPATMI/EPS trong report KHỚP data files (±5%). KHÔNG bịa.",
  "priority": "critical",
  "method": "data_accuracy_check",
  "status": "fail",
  "evidence": {
    "checked": 11,
    "mismatches": [
      "revenue_ty[2022]: ground_truth=33,876.5 not found in report (±5%)",
      "revenue_ty[2023]: ground_truth=33,136.9 not found in report (±5%)",
      "revenue_ty[2024]: ground_truth=37,822.8 not found in report (±5%)",
      "revenue_ty[2025]: ground_truth=34,976.0 not found in report (±5%)"
    ],
    "ground_truth_file": "data/financials.json"
  },
  "verified_at": "2026-07-12T13:58:43.556903",
  "artifact": "/Users/bobo/ZCodeProject/skill-harness-evaluator-work/p1-cycle/MUT-DATA-REV-002-work/MUT-DATA-REV-002.html"
}