{
  "requirement_id": "REQ-028",
  "text": "Chart render-readiness: mỗi canvas ID referenced trong Chart() phải có HTML element, không duplicate, có DATA object. (Học từ PNJ v2 test: 27/27 PASS nhưng charts vẫn crash do duplicate canvas sau </body>.)",
  "priority": "high",
  "method": "chart_runtime_check",
  "status": "fail",
  "evidence": {
    "canvas_ids_found": [
      "chartHistRev",
      "chartSegMix",
      "chartThesisCapex",
      "chartValPE",
      "chartPeerScatter",
      "chartBSDt",
      "chartBSDt2",
      "chartTechPrice",
      "chartTechRSI",
      "chartProfileDD",
      "chartProfileDist"
    ],
    "chart_ids_referenced": [
      "chartHistCash",
      "chartThesisCapex",
      "chartBSDt2",
      "chartPeerScatter",
      "chartSegMix",
      "chartHistRev",
      "chartProfileDist",
      "chartValPE",
      "chartBSDt",
      "chartReturns",
      "chartThesisRPO",
      "chartTechRSI",
      "chartTechPrice",
      "chartProfileDD"
    ],
    "missing_canvas": [
      "chartHistCash",
      "chartReturns",
      "chartThesisRPO"
    ],
    "duplicates": {},
    "has_data_object": true,
    "has_chart_js": true,
    "issues": [
      "Chart references canvas not in HTML: ['chartHistCash', 'chartReturns', 'chartThesisRPO']"
    ]
  },
  "verified_at": "2026-07-12T13:01:31.542535",
  "artifact": "/Users/bobo/ZCodeProject/skill-harness-evaluator-work/runs/run-01/clean-control.html"
}