{
  "2Y": [
    {
      "date": "2026-04-03",
      "yield": 3.6086
    },
    {
      "date": "2026-04-10",
      "yield": 3.6033
    },
    {
      "date": "2026-04-17",
      "yield": 3.659
    },
    {
      "date": "2026-04-24",
      "yield": 3.6568
    },
    {
      "date": "2026-05-08",
      "yield": 3.7157
    },
    {
      "date": "2026-05-15",
      "yield": 3.7149
    },
    {
      "date": "2026-05-22",
      "yield": 3.7558
    },
    {
      "date": "2026-05-29",
      "yield": 3.7676
    },
    {
      "date": "2026-06-05",
      "yield": 3.7967
    },
    {
      "date": "2026-06-12",
      "yield": 3.8222
    },
    {
      "date": "2026-06-19",
      "yield": 3.8305
    },
    {
      "date": "2026-06-26",
      "yield": 3.8608
    }
  ],
  "5Y": [
    {
      "date": "2026-04-03",
      "yield": 3.8554
    },
    {
      "date": "2026-04-03",
      "yield": 4.2874
    },
    {
      "date": "2026-04-10",
      "yield": 3.8061
    },
    {
      "date": "2026-04-10",
      "yield": 4.2786
    },
    {
      "date": "2026-04-17",
      "yield": 3.9192
    },
    {
      "date": "2026-04-17",
      "yield": 4.3707
    },
    {
      "date": "2026-04-24",
      "yield": 3.9195
    },
    {
      "date": "2026-04-24",
      "yield": 4.3481
    },
    {
      "date": "2026-05-08",
      "yield": 3.9647
    },
    {
      "date": "2026-05-08",
      "yield": 4.3886
    },
    {
      "date": "2026-05-15",
      "yield": 3.9745
    },
    {
      "date": "2026-05-15",
      "yield": 4.3867
    },
    {
      "date": "2026-05-22",
      "yield": 3.9729
    },
    {
      "date": "2026-05-22",
      "yield": 4.3814
    },
    {
      "date": "2026-05-29",
      "yield": 4.005
    },
    {
      "date": "2026-05-29",
      "yield": 4.4509
    },
    {
      "date": "2026-06-05",
      "yield": 4.0702
    },
    {
      "date": "2026-06-05",
      "yield": 4.4755
    },
    {
      "date": "2026-06-12",
      "yield": 4.1076
    },
    {
      "date": "2026-06-12",
      "yield": 4.5063
    },
    {
      "date": "2026-06-19",
      "yield": 4.1095
    },
    {
      "date": "2026-06-19",
      "yield": 4.551
    },
    {
      "date": "2026-06-26",
      "yield": 4.1099
    },
    {
      "date": "2026-06-26",
      "yield": 4.5794
    }
  ],
  "10Y": [
    {
      "date": "2026-04-03",
      "yield": 4.1356
    },
    {
      "date": "2026-04-10",
      "yield": 4.0793
    },
    {
      "date": "2026-04-17",
      "yield": 4.218
    },
    {
      "date": "2026-04-24",
      "yield": 4.2058
    },
    {
      "date": "2026-05-08",
      "yield": 4.2422
    },
    {
      "date": "2026-05-15",
      "yield": 4.2484
    },
    {
      "date": "2026-05-22",
      "yield": 4.2303
    },
    {
      "date": "2026-05-29",
      "yield": 4.2888
    },
    {
      "date": "2026-06-05",
      "yield": 4.3367
    },
    {
      "date": "2026-06-12",
      "yield": 4.3722
    },
    {
      "date": "2026-06-19",
      "yield": 4.4011
    },
    {
      "date": "2026-06-26",
      "yield": 4.4065
    }
  ]
}