{
  "answer": "Thông tư 99/2026 có hiệu lực từ ngày 15/05/2026 [tt99_2026, p.1, 'Hiệu lực', 'CÓ HIỆU LỰC từ ngày 15/05/2026']. Khoản 2 Điều 2 quy định doanh nghiệp chưa niêm yết có thể áp dụng tự nguyện [tt99_2026, p.1, 'Điều 2', 'Khoản 2. Doanh nghiệp chưa niêm yết có thể áp dụng tự nguyện'].",
  "citations": [
    {
      "file": "tt99_2026",
      "page": 1,
      "section": "Hiệu lực",
      "quote": "CÓ HIỆU LỰC từ ngày 15/05/2026",
      "note": null
    },
    {
      "file": "tt99_2026",
      "page": 1,
      "section": "Điều 2",
      "quote": "Khoản 2. Doanh nghiệp chưa niêm yết có thể áp dụng tự nguyện",
      "note": null
    }
  ],
  "evidence": [
    {
      "page": 1,
      "snippet": "CÓ HIỆU LỰC từ ngày 15/05/2026"
    },
    {
      "page": 1,
      "snippet": "Khoản 2. Doanh nghiệp chưa niêm yết có thể áp dụng tự nguyện"
    }
  ],
  "confidence": 0.9,
  "abstention_flag": false,
  "abstention_reason": null,
  "outside_knowledge_used": false,
  "warnings": []
}